Workbook

Sheet README
A1: Hospital Care Analytics Dataset
D2: Sheet | E2: Rows | F2: Description
A3: Dataset purpose | B3: Synthetic health operations dataset for a moderate-to-hard Week 10 final exam using Excel, Access, and Power BI. | D3: Patient_Visits | E3: 1400 | F3: Main transaction table of appointments, admissions, costs, follow-up, satisfaction, and readmission.
A4: Real-life story | B4: A hospital network wants to reduce no-shows, long stays, cost overruns, missed follow-ups, and 30-day readmissions. | D4: Patients | E4: 600 | F4: Patient demographics, area, chronic condition, smoking status, and risk group.
A5: Important note | B5: All patient and doctor names are fictional. This dataset does not contain real patient information. | D5: Doctors | E5: 60 | F5: Doctor lookup table with department, specialization, fee, experience, and capacity.
A6: Suggested student role | B6: Healthcare Data Analyst for hospital management. | D6: Departments | E6: 10 | F6: Hospital department lookup table with budgets and performance targets.
A7: Main analytical question | B7: Which departments, doctors, diagnoses, insurance groups, and patient risk groups are linked with higher cost, longer stays, missed follow-ups, and readmission? | D7: Diagnosis_Guide | E7: 30 | F7: Reference table for diagnosis, disease category, severity, standard cost, expected stay, and department.
A8: Data quality challenges intentionally included | B8: Some inconsistent appointment status labels, inconsistent gender case, area trailing spaces, and limited missing values in doctor, treatment cost, satisfaction, and follow-up fields. | D8: Insurance_Plans | E8: 7 | F8: Insurance lookup table with coverage, claim processing days, and co-pay.

Sheet Patient_Visits
A1: Visit ID | B1: Patient ID | C1: Appointment Date | D1: Appointment Time | E1: Appointment Status | F1: Admission Date | G1: Discharge Date | H1: Department ID | I1: Doctor ID | J1: Diagnosis Code | K1: Visit Type | L1: Admission Source | M1: Treatment Cost | N1: Lab Cost | O1: Medicine Cost | P1: Room Cost | Q1: Total Bill | R1: Insurance Plan ID | S1: Claim Status | T1: Patient Payable | U1: Patient Satisfaction | V1: Follow Up Required | W1: Follow Up Date | X1: Follow Up Completed | Y1: Readmitted Within 30 Days | Z1: Discharge Outcome
A2: V10001 | B2: P2181 | C2: 46071 | D2: 12:45 | E2: Cancelled | H2: D09 | I2: DR152 | J2: DG22 | K2: Outpatient | L2: Doctor Referral | R2: IP06 | S2: Not Applicable | V2: No | X2: Not Required | Z2: Not Treated
A3: V10002 | B3: P2449 | C3: 46032 | D3: 11:00 | E3: Attended | F3: 46032 | G3: 46034 | H3: D09 | I3: DR150 | J3: DG24 | K3: Inpatient | L3: Emergency Walk-in | M3: 7600 | N3: 1350 | O3: 1700 | P3: 5000 | Q3: 17450 | R3: IP01 | S3: Approved | T3: 8150 | U3: 2 | V3: No | X3: Not Required | Y3: Yes | Z3: Improved
A4: V10003 | B4: P2550 | C4: 46082 | D4: 09:00 | E4: Attended | F4: 46082 | G4: 46082 | H4: D04 | I4: DR123 | J4: DG08 | K4: Inpatient | L4: Doctor Referral | M4: 6300 | N4: 900 | O4: 650 | P4: 0 | Q4: 9650 | R4: IP04 | S4: Pending | T4: 3310 | U4: 5 | V4: No | X4: Not Required | Y4: No | Z4: Improved
A5: V10004 | B5: P2226 | C5: 46132 | D5: 13:45 | E5: Attended | F5: 46132 | G5: 46137 | H5: D02 | I5: DR108 | J5: DG02 | K5: Surgery | L5: Scheduled Appointment | M5: 59900 | N5: 6800 | O5: 7050 | P5: 15000 | Q5: 89950 | R5: IP05 | S5: Not Applicable | T5: 89950 | U5: 5 | V5: Yes | W5: 46149 | X5: Yes | Y5: No | Z5: Recovered
A6: V10005 | B6: P2017 | C6: 46024 | D6: 08:15 | E6: Cancelled | H6: D09 | I6: DR149 | J6: DG24 | K6: Inpatient | L6: Emergency Walk-in | R6: IP06 | S6: Not Applicable | V6: No | X6: Not Required | Z6: Not Treated
A7: V10006 | B7: P2488 | C7: 46059 | D7: 12:45 | E7: Attended | F7: 46059 | G7: 46067 | H7: D08 | I7: DR144 | J7: DG21 | K7: Surgery | L7: Scheduled Appointment | M7: 63500 | N7: 8950 | O7: 7200 | P7: 28000 | Q7: 109450 | R7: IP02 | S7: Approved | T7: 39010 | U7: 3 | V7: Yes | W7: 46075 | X7: No | Y7: No | Z7: Stable
A8: V10007 | B8: P2214 | C8: 46051 | D8: 10:45 | E8: Attended | F8: 46051 | G8: 46051 | H8: D05 | I8: DR126 | J8: DG11 | K8: Outpatient | L8: Scheduled Appointment | M8: 20100 | N8: 3250 | O8: 4300 | P8: 0 | Q8: 28450 | R8: IP01 | S8: Approved | T8: 13100 | U8: 4 | V8: No | X8: Not Required | Y8: No | Z8: Recovered
A9: V10008 | B9: P2334 | C9: 46106 | D9: 11:00 | E9: Attended | F9: 46106 | G9: 46106 | H9: D05 | I9: DR130 | J9: DG10 | K9: Outpatient | L9: Scheduled Appointment | M9: 5800 | N9: 750 | O9: 1000 | P9: 0 | Q9: 8350 | R9: IP06 | S9: Approved | T9: 2910 | U9: 5 | V9: No | X9: Not Required | Y9: No | Z9: Improved
A10: V10009 | B10: P2344 | C10: 46168 | D10: 08:30 | E10: Attended | F10: 46168 | G10: 46172 | H10: D03 | I10: DR118 | J10: DG06 | K10: Emergency | L10: Emergency Walk-in | M10: 42600 | N10: 6150 | O10: 8150 | P10: 12000 | Q10: 69900 | R10: IP04 | S10: Approved | T10: 18380 | U10: 3 | V10: Yes | W10: 46185 | X10: No | Y10: No | Z10: Stable
A11: V10010 | B11: P2253 | C11: 46171 | D11: 11:15 | E11: Cancelled | H11: D02 | I11: DR110 | J11: DG03 | K11: Outpatient | L11: Doctor Referral | R11: IP04 | S11: Not Applicable | V11: No | X11: Not Required | Z11: Not Treated
A12: V10011 | B12: P2517 | C12: 46123 | D12: 15:00 | E12: Attended | F12: 46123 | G12: 46123 | H12: D02 | I12: DR111 | J12: DG02 | K12: Outpatient | L12: Scheduled Appointment | M12: 43000 | N12: 5000 | O12: 5850 | P12: 0 | Q12: 55850 | R12: IP07 | S12: Approved | T12: 30920 | V12: Yes | W12: 46132 | X12: No | Y12: No | Z12: Improved
A13: V10012 | B13: P2380 | C13: 46023 | D13: 09:45 | E13: Cancelled | H13: D07 | I13: DR142 | J13: DG16 | K13: Outpatient | L13: Emergency Walk-in | R13: IP03 | S13: Not Applicable | V13: No | X13: Not Required | Z13: Not Treated
A14: V10013 | B14: P2556 | C14: 46043 | D14: 17:30 | E14: Attended | F14: 46043 | G14: 46043 | H14: D08 | I14: DR144 | J14: DG19 | K14: Outpatient | L14: Transfer from Clinic | M14: 27500 | N14: 3200 | O14: 3450 | P14: 0 | Q14: 35950 | R14: IP04 | S14: Approved | T14: 9890 | U14: 5 | V14: No | X14: Not Required | Y14: No | Z14: Recovered
A15: V10014 | B15: P2215 | C15: 46105 | D15: 13:30 | E15: Attended | F15: 46105 | G15: 46107 | H15: D10 | I15: DR156 | J15: DG25 | K15: Inpatient | L15: Doctor Referral | M15: 22000 | N15: 2850 | O15: 3950 | P15: 5000 | Q15: 36300 | R15: IP03 | S15: Approved | T15: 6650 | U15: 5 | V15: No | X15: Not Required | Y15: No | Z15: Stable
A16: V10015 | B16: P2068 | C16: 46045 | D16: 09:45 | E16: Cancelled | H16: D04 | I16: DR122 | J16: DG09 | K16: Surgery | L16: Doctor Referral | R16: IP03 | S16: Not Applicable | V16: No | X16: Not Required | Z16: Not Treated
A17: V10016 | B17: P2115 | C17: 46061 | D17: 11:00 | E17: Attended | F17: 46061 | G17: 46064 | H17: D09 | I17: DR152 | J17: DG22 | K17: Surgery | L17: Emergency Walk-in | M17: 39000 | N17: 3850 | O17: 4050 | P17: 9000 | Q17: 58400 | R17: IP05 | S17: Not Applicable | T17: 58400 | U17: 5 | V17: Yes | W17: 46076 | X17: Yes | Y17: No | Z17: Improved
A18: V10017 | B18: P2581 | C18: 46066 | D18: 12:15 | E18: Attended | F18: 46066 | G18: 46074 | H18: D02 | I18: DR109 | J18: DG02 | K18: Surgery | L18: Scheduled Appointment | M18: 55900 | N18: 5400 | O18: 13350 | P18: 48000 | Q18: 123850 | R18: IP02 | S18: Rejected | T18: 44050 | U18: 3 | V18: No | X18: Not Required | Y18: No | Z18: Recovered
A19: V10018 | B19: P2379 | C19: 46031 | D19: 13:30 | E19: Attended | F19: 46031 | G19: 46033 | H19: D04 | I19: DR123 | J19: DG08 | K19: Inpatient | L19: Transfer from Clinic | M19: 10000 | N19: 1550 | O19: 2400 | P19: 7000 | Q19: 22750 | R19: IP01 | S19: Rejected | T19: 10540 | U19: 4 | V19: No | X19: Not Required | Y19: No | Z19: Recovered
A20: V10019 | B20: P2151 | C20: 46136 | D20: 13:00 | E20: Attended | F20: 46136 | G20: 46144 | H20: D09 | I20: DR154 | J20: DG23 | K20: Emergency | L20: Doctor Referral | M20: 63500 | N20: 6500 | O20: 9750 | P20: 28000 | Q20: 108550 | R20: IP01 | S20: Approved | T20: 49150 | V20: Yes | W20: 46154 | X20: No | Y20: No | Z20: Improved
A21: V10020 | B21: P2525 | C21: 46104 | D21: 17:00 | E21: Cancelled | H21: D03 | I21: DR116 | J21: DG06 | K21: Outpatient | L21: Scheduled Appointment | R21: IP03 | S21: Not Applicable | V21: No | X21: Not Required | Z21: Not Treated
A22: V10021 | B22: P2396 | C22: 46111 | D22: 13:30 | E22: Rescheduled | H22: D06 | I22: DR133 | J22: DG13 | K22: Surgery | L22: Scheduled Appointment | R22: IP04 | S22: Not Applicable | V22: No | X22: Not Required | Z22: Not Treated
A23: V10022 | B23: P2426 | C23: 46064 | D23: 14:45 | E23: Attended | F23: 46064 | G23: 46068 | H23: D09 | I23: DR151 | J23: DG23 | K23: Inpatient | L23: Doctor Referral | M23: 54800 | N23: 9500 | O23: 10350 | P23: 18000 | Q23: 93850 | R23: IP01 | S23: Approved | T23: 42530 | U23: 5 | V23: No | X23: Not Required | Y23: No | Z23: Recovered
A24: V10023 | B24: P2044 | C24: 46172 | D24: 12:45 | E24: Attended | F24: 46172 | G24: 46184 | H24: D10 | I24: DR157 | J24: DG27 | K24: Inpatient | L24: Doctor Referral | M24: 103400 | N24: 16900 | O24: 17650 | P24: 42000 | Q24: 182450 | R24: IP03 | S24: Approved | T24: 28570 | U24: 3 | V24: Yes | W24: 46194 | X24: Yes | Y24: No | Z24: Recovered
A25: V10024 | B25: P2265 | C25: 46053 | D25: 13:00 | E25: No-show | H25: D09 | I25: DR152 | J25: DG22 | K25: Outpatient | L25: Emergency Walk-in | R25: IP06 | S25: Not Applicable | V25: No | X25: Not Required | Z25: Not Treated
A26: V10025 | B26: P2139 | C26: 46092 | D26: 13:45 | E26: Attended | F26: 46092 | G26: 46092 | H26: D04 | I26: DR119 | J26: DG08 | K26: Surgery | L26: Doctor Referral | M26: 7300 | N26: 1150 | O26: 950 | P26: 0 | Q26: 11200 | R26: IP01 | S26: Approved | T26: 5340 | U26: 5 | V26: No | X26: Not Required | Y26: No | Z26: Improved
A27: V10026 | B27: P2148 | C27: 46095 | D27: 13:45 | E27: Attended | F27: 46095 | G27: 46097 | H27: D02 | I27: DR111 | J27: DG01 | K27: Surgery | L27: Doctor Referral | M27: 14800 | N27: 1500 | O27: 1900 | P27: 12000 | Q27: 32200 | R27: IP04 | S27: Pending | T27: 8950 | U27: 5 | V27: No | X27: Not Required | Y27: No | Z27: Stable
A28: V10027 | B28: P2135 | C28: 46112 | D28: 12:30 | E28: Attended | F28: 46112 | G28: 46112 | H28: D01 | I28: DR104 | J28: DG28 | K28: Outpatient | L28: Emergency Walk-in | M28: 33000 | N28: 4950 | O28: 6700 | P28: 0 | Q28: 47150 | R28: IP02 | S28: Approved | T28: 17200 | U28: 4 | V28: No | X28: Not Required | Y28: No | Z28: Stable
A29: V10028 | B29: P2526 | C29: 46053 | D29: 12:00 | E29: Attended | F29: 46053 | G29: 46058 | H29: D08 | I29: DR146 | J29: DG21 | K29: Inpatient | L29: Scheduled Appointment | M29: 42700 | N29: 7250 | O29: 5450 | P29: 17500 | Q29: 74400 | R29: IP01 | S29: Approved | T29: 33780 | U29: 4 | V29: Yes | W29: 46069 | X29: No | Y29: No | Z29: Stable
A30: V10029 | B30: P2593 | C30: 46078 | D30: 11:30 | E30: Attended | F30: 46078 | G30: 46085 | H30: D09 | I30: DR153 | J30: DG22 | K30: Emergency | L30: Doctor Referral | M30: 57700 | N30: 8650 | O30: 7350 | P30: 17500 | Q30: 93200 | R30: IP01 | S30: Approved | T30: 42240 | U30: 3 | V30: Yes | W30: 46095 | X30: Yes | Y30: No | Z30: Recovered
A31: V10030 | B31: P2571 | C31: 46106 | D31: 15:00 | E31: Attended | F31: 46107 | G31: 46112 | H31: D08 | I31: DR143 | J31: DG21 | K31: Inpatient | L31: Scheduled Appointment | M31: 57600 | N31: 9550 | O31: 7400 | P31: 12500 | Q31: 87850 | R31: IP06 | S31: Pending | T31: 26760 | U31: 3 | V31: No | X31: Not Required | Y31: Yes | Z31: Recovered
A32: V10031 | B32: P2405 | C32: 46049 | D32: 10:00 | E32: Attended | F32: 46050 | G32: 46056 | H32: D06 | I32: DR135 | J32: DG13 | K32: Surgery | L32: Scheduled Appointment | M32: 58300 | N32: 8800 | O32: 10900 | P32: 21000 | Q32: 100500 | R32: IP05 | S32: Not Applicable | T32: 100500 | U32: 5 | V32: No | X32: Not Required | Y32: No | Z32: Against Medical Advice
A33: V10032 | B33: P2126 | C33: 46082 | D33: 10:00 | E33: Attended | F33: 46082 | G33: 46083 | H33: D05 | I33: DR128 | J33: DG11 | K33: Outpatient | L33: Doctor Referral | M33: 23400 | N33: 3450 | O33: 2900 | P33: 6000 | Q33: 36750 | R33: IP04 | S33: Approved | T33: 10090 | U33: 5 | V33: No | X33: Not Required | Y33: No | Z33: Recovered
A34: V10033 | B34: P2352 | C34: 46162 | D34: 08:00 | E34: Rescheduled | H34: D09 | I34: DR153 | J34: DG23 | K34: Emergency | L34: Doctor Referral | R34: IP04 | S34: Not Applicable | V34: No | X34: Not Required | Z34: Not Treated
A35: V10034 | B35: P2323 | C35: 46140 | D35: 08:00 | E35: Attended | F35: 46140 | G35: 46142 | H35: D10 | I35: DR158 | J35: DG26 | K35: Inpatient | L35: Scheduled Appointment | M35: 47900 | N35: 6150 | O35: 5600 | P35: 9000 | Q35: 70150 | R35: IP04 | S35: Approved | T35: 18440 | U35: 4 | V35: No | X35: Not Required | Y35: No | Z35: Recovered
A36: V10035 | B36: P2362 | C36: 46105 | D36: 08:00 | E36: Attended | F36: 46105 | G36: 46105 | H36: D09 | I36: DR151 | J36: DG23 | K36: Outpatient | L36: Emergency Walk-in | M36: 49400 | N36: 6050 | O36: 12300 | P36: 0 | Q36: 68950 | R36: IP03 | S36: Approved | T36: 11540 | U36: 4 | V36: Yes | W36: 46115 | X36: Yes | Y36: No | Z36: Recovered
A37: V10036 | B37: P2433 | C37: 46091 | D37: 08:45 | E37: Attended | F37: 46092 | G37: 46096 | H37: D07 | I37: DR140 | J37: DG18 | K37: Surgery | L37: Emergency Walk-in | M37: 41800 | N37: 4200 | O37: 7300 | P37: 14000 | Q37: 68300 | R37: IP01 | S37: Approved | T37: 31030 | U37: 4 | V37: Yes | W37: 46113 | X37: No | Y37: No | Z37: Recovered
A38: V10037 | B38: P2095 | C38: 46047 | D38: 17:30 | E38: Attended | F38: 46048 | G38: 46051 | H38: D10 | I38: DR159 | J38: DG25 | K38: Inpatient | L38: Emergency Walk-in | M38: 20400 | N38: 3250 | O38: 4050 | P38: 10500 | Q38: 40000 | R38: IP03 | S38: Approved | T38: 7200 | U38: 5 | V38: No | X38: Not Required | Y38: No | Z38: Improved
A39: V10038 | B39: P2020 | C39: 46070 | D39: 17:45 | E39: Attended | F39: 46071 | G39: 46076 | H39: D08 | I39: DR147 | J39: DG20 | K39: Surgery | L39: Scheduled Appointment | M39: 90800 | N39: 15500 | O39: 21800 | P39: 12500 | Q39: 142400 | R39: IP03 | S39: Approved | T39: 22560 | U39: 3 | V39: Yes | W39: 46085 | X39: No | Y39: No | Z39: Stable
A40: V10039 | B40: P2274 | C40: 46064 | D40: 12:15 | E40: Attended | F40: 46064 | G40: 46064 | H40: D10 | I40: DR160 | J40: DG27 | K40: Outpatient | L40: Doctor Referral | M40: 83200 | N40: 14900 | O40: 13600 | P40: 0 | Q40: 112700 | R40: IP06 | S40: Approved | T40: 34210 | U40: 5 | V40: Yes | W40: 46071 | X40: Yes | Y40: No | Z40: Stable
A41: V10040 | B41: P2086 | C41: 46039 | D41: 14:30 | E41: Attended | F41: 46039 | G41: 46045 | H41: D03 | I41: DR115 | J41: DG04 | K41: Emergency | L41: Emergency Walk-in | M41: 64300 | N41: 9400 | O41: 12050 | P41: 36000 | Q41: 123750 | R41: IP02 | S41: Pending | T41: 44010 | U41: 4 | V41: Yes | W41: 46053 | X41: No | Y41: No | Z41: Stable
A42: V10041 | B42: P2110 | C42: 46135 | D42: 14:30 | E42: Missed | H42: D03 | I42: DR115 | J42: DG05 | K42: Emergency | L42: Doctor Referral | R42: IP05 | S42: Not Applicable | V42: No | X42: Not Required | Z42: Not Treated
A43: V10042 | B43: P2434 | C43: 46094 | D43: 10:30 | E43: Attended | F43: 46094 | G43: 46095 | H43: D07 | I43: DR138 | J43: DG17 | K43: Outpatient | L43: Emergency Walk-in | N43: 1050 | O43: 1200 | P43: 3000 | Q43: 13750 | R43: IP02 | S43: Approved | T43: 5510 | U43: 3 | V43: No | X43: Not Required | Y43: No | Z43: Recovered
A44: V10043 | B44: P2262 | C44: 46099 | D44: 11:15 | E44: Cancelled | H44: D05 | I44: DR126 | J44: DG10 | K44: Emergency | L44: Scheduled Appointment | R44: IP04 | S44: Not Applicable | V44: No | X44: Not Required | Z44: Not Treated
A45: V10044 | B45: P2035 | C45: 46148 | D45: 15:45 | E45: Cancelled | H45: D05 | I45: DR125 | J45: DG10 | K45: Inpatient | L45: Scheduled Appointment | R45: IP01 | S45: Not Applicable | V45: No | X45: Not Required | Z45: Not Treated
A46: V10045 | B46: P2165 | C46: 46039 | D46: 13:45 | E46: Attended | F46: 46040 | G46: 46044 | H46: D08 | I46: DR147 | J46: DG20 | K46: Emergency | L46: Scheduled Appointment | M46: 57000 | N46: 7100 | O46: 11200 | P46: 10000 | Q46: 87100 | R46: IP03 | S46: Approved | T46: 14270 | U46: 5 | V46: Yes | W46: 46052 | X46: Yes | Y46: No | Z46: Improved
A47: V10046 | B47: P2137 | C47: 46106 | D47: 12:15 | E47: Attended | F47: 46107 | G47: 46108 | H47: D04 | I47: DR124 | J47: DG09 | K47: Outpatient | L47: Emergency Walk-in | M47: 66800 | N47: 11700 | O47: 15950 | P47: 6000 | Q47: 102250 | R47: IP04 | S47: Pending | T47: 26460 | U47: 4 | V47: Yes | W47: 46126 | X47: No | Y47: Yes | Z47: Recovered
A48: V10047 | B48: P2121 | C48: 46134 | D48: 15:45 | E48: Attended | F48: 46134 | G48: 46136 | H48: D02 | I48: DR111 | J48: DG01 | K48: Emergency | L48: Doctor Referral | M48: 16500 | N48: 2750 | O48: 3150 | P48: 7000 | Q48: 31400 | R48: IP05 | S48: Not Applicable | T48: 31400 | U48: 5 | V48: Yes | W48: 46145 | X48: Yes | Y48: No | Z48: Recovered
A49: V10048 | B49: P2470 | C49: 46057 | D49: 13:45 | E49: Attended | F49: 46057 | G49: 46068 | H49: D03 | I49: DR116 | J49: DG04 | K49: Emergency | L49: Scheduled Appointment | M49: 61800 | N49: 7000 | O49: 8350 | P49: 38500 | Q49: 117450 | R49: IP07 | S49: Pending | T49: 64800 | V49: No | X49: Not Required | Y49: No | Z49: Improved
A50: V10049 | B50: P2136 | C50: 46033 | D50: 17:15 | E50: Attended | F50: 46033 | G50: 46033 | H50: D01 | I50: DR105 | J50: DG30 | K50: Outpatient | L50: Scheduled Appointment | M50: 5900 | N50: 650 | O50: 1450 | P50: 0 | Q50: 9000 | R50: IP03 | S50: Rejected | T50: 2550 | U50: 4 | V50: Yes | W50: 46045 | X50: No | Y50: No | Z50: Stable
A51: V10050 | B51: P2324 | C51: 46061 | D51: 16:45 | E51: Attended | F51: 46061 | G51: 46061 | H51: D09 | I51: DR152 | J51: DG22 | K51: Outpatient | L51: Doctor Referral | M51: 50800 | N51: 4650 | O51: 11900 | P51: 0 | Q51: 69850 | R51: IP03 | S51: Approved | T51: 11680 | U51: 3 | V51: No | X51: Not Required | Y51: No | Z51: Stable
A52: V10051 | B52: P2185 | C52: 46153 | D52: 12:15 | E52: Attended | F52: 46153 | G52: 46156 | H52: D10 | I52: DR160 | J52: DG26 | K52: Surgery | L52: Emergency Walk-in | M52: 43100 | N52: 6350 | O52: 10050 | P52: 7500 | Q52: 68000 | R52: IP02 | S52: Rejected | T52: 24500 | U52: 5 | V52: Yes | W52: 46168 | X52: Yes | Y52: No | Z52: Recovered
A53: V10052 | B53: P2276 | C53: 46107 | D53: 08:45 | E53: Attended | F53: 46107 | G53: 46113 | H53: D08 | I53: DR143 | J53: DG21 | K53: Emergency | L53: Scheduled Appointment | M53: 58100 | N53: 6300 | O53: 12750 | P53: 15000 | Q53: 92950 | R53: IP04 | S53: Approved | T53: 24140 | U53: 4 | V53: Yes | W53: 46124 | X53: Yes | Y53: No | Z53: Stable
A54: V10053 | B54: P2158 | C54: 46133 | D54: 12:15 | E54: Attended | F54: 46133 | G54: 46133 | H54: D04 | I54: DR122 | J54: DG07 | K54: Outpatient | L54: Emergency Walk-in | M54: 41000 | N54: 5000 | O54: 8750 | P54: 0 | Q54: 57250 | R54: IP05 | S54: Not Applicable | T54: 57250 | U54: 5 | V54: No | X54: Not Required | Y54: No | Z54: Improved
A55: V10054 | B55: P2159 | C55: 46157 | D55: 09:30 | E55: Attended | F55: 46157 | G55: 46161 | H55: D01 | I55: DR105 | J55: DG29 | K55: Inpatient | L55: Emergency Walk-in | M55: 38700 | N55: 4050 | O55: 6350 | P55: 24000 | Q55: 74100 | R55: IP01 | S55: Approved | T55: 33640 | U55: 4 | V55: Yes | W55: 46169 | X55: Yes | Y55: No | Z55: Improved
A56: V10055 | B56: P2516 | C56: 46141 | D56: 10:15 | E56: Missed | H56: D02 | I56: DR112 | J56: DG01 | K56: Emergency | L56: Emergency Walk-in | R56: IP05 | S56: Not Applicable | V56: No | X56: Not Required | Z56: Not Treated
A57: V10056 | B57: P2466 | C57: 46090 | D57: 13:15 | E57: Attended | F57: 46090 | G57: 46090 | H57: D10 | I57: DR158 | J57: DG26 | K57: Outpatient | L57: Transfer from Clinic | M57: 28300 | N57: 2600 | O57: 3550 | P57: 0 | Q57: 35950 | R57: IP03 | S57: Approved | T57: 6590 | U57: 5 | V57: No | X57: Not Required | Y57: No | Z57: Recovered
A58: V10057 | B58: P2405 | C58: 46055 | D58: 10:00 | E58: Attended | F58: 46055 | G58: 46060 | H58: D10 | I58: DR155 | J58: DG27 | K58: Emergency | L58: Scheduled Appointment | M58: 71300 | N58: 10350 | O58: 14100 | P58: 22500 | Q58: 119450 | R58: IP05 | S58: Not Applicable | T58: 119450 | U58: 4 | V58: No | X58: Not Required | Y58: Yes | Z58: Improved
A59: V10058 | B59: P2456 | C59: 46028 | D59: 15:15 | E59: Attended | F59: 46028 | G59: 46034 | H59: D01 | I59: DR104 | J59: DG29 | K59: Inpatient | L59: Doctor Referral | M59: 52900 | N59: 6850 | O59: 9900 | P59: 36000 | Q59: 108150 | R59: IP07 | S59: Approved | T59: 59680 | U59: 3 | V59: Yes | W59: 46049 | X59: Yes | Y59: No | Z59: Recovered
A60: V10059 | B60: P2275 | C60: 46144 | D60: 09:45 | E60: Attended | F60: 46144 | G60: 46149 | H60: D01 | I60: DR104 | J60: DG28 | K60: Emergency | L60: Emergency Walk-in | M60: 40200 | N60: 5000 | O60: 7100 | P60: 30000 | Q60: 84800 | R60: IP06 | S60: Approved | T60: 25840 | U60: 2 | V60: Yes | W60: 46169 | X60: No | Y60: No | Z60: Recovered
A61: V10060 | B61: P2369 | C61: 46076 | D61: 12:00 | E61: Attended | F61: 46077 | G61: 46077 | H61: D10 | I61: DR156 | J61: DG27 | K61: Outpatient | L61: Doctor Referral | M61: 71300 | N61: 6050 | O61: 7300 | P61: 0 | Q61: 87150 | R61: IP06 | S61: Approved | T61: 26550 | U61: 3 | V61: Yes | W61: 46097 | X61: No | Y61: No | Z61: Recovered
A62: V10061 | B62: P2349 | C62: 46165 | D62: 12:15 | E62: No Show | H62: D10 | I62: DR155 | J62: DG26 | K62: Inpatient | L62: Doctor Referral | R62: IP01 | S62: Not Applicable | V62: No | X62: Not Required | Z62: Not Treated
A63: V10062 | B63: P2449 | C63: 46050 | D63: 17:00 | E63: No-show | H63: D10 | I63: DR155 | J63: DG26 | K63: Outpatient | L63: Doctor Referral | R63: IP02 | S63: Not Applicable | V63: No | X63: Not Required | Z63: Not Treated
A64: V10063 | B64: P2371 | C64: 46136 | D64: 16:45 | E64: Attended | F64: 46136 | G64: 46136 | H64: D03 | I64: DR115 | J64: DG04 | K64: Outpatient | L64: Scheduled Appointment | M64: 59900 | N64: 10600 | O64: 12900 | P64: 0 | Q64: 85400 | R64: IP01 | S64: Pending | T64: 38730 | U64: 4 | V64: Yes | W64: 46147 | X64: Yes | Y64: Yes | Z64: Recovered
A65: V10064 | B65: P2543 | C65: 46058 | D65: 14:45 | E65: Cancelled | H65: D07 | I65: DR138 | J65: DG16 | K65: Surgery | L65: Emergency Walk-in | R65: IP06 | S65: Not Applicable | V65: No | X65: Not Required | Z65: Not Treated
A66: V10065 | B66: P2371 | C66: 46060 | D66: 08:00 | E66: Attended | F66: 46060 | G66: 46060 | H66: D01 | I66: DR104 | J66: DG28 | K66: Outpatient | L66: Doctor Referral | M66: 42400 | N66: 7550 | O66: 10450 | P66: 0 | Q66: 62900 | R66: IP05 | S66: Not Applicable | T66: 62900 | U66: 5 | V66: No | X66: Not Required | Y66: No | Z66: Improved
A67: V10066 | B67: P2541 | C67: 46126 | D67: 15:15 | E67: Cancelled | H67: D07 | I67: DR138 | J67: DG18 | K67: Inpatient | L67: Emergency Walk-in | R67: IP03 | S67: Not Applicable | V67: No | X67: Not Required | Z67: Not Treated
A68: V10067 | B68: P2415 | C68: 46044 | D68: 08:30 | E68: Attended | F68: 46044 | G68: 46046 | H68: D09 | I68: DR151 | J68: DG24 | K68: Emergency | L68: Scheduled Appointment | M68: 6500 | N68: 850 | O68: 950 | P68: 7000 | Q68: 16500 | R68: IP05 | S68: Not Applicable | T68: 16500 | U68: 3 | V68: Yes | W68: 46053 | X68: No | Y68: No | Z68: Stable
A69: V10068 | B69: P2062 | C69: 46152 | D69: 13:00 | E69: Attended | F69: 46152 | G69: 46152 | H69: D01 | I69: DR103 | J69: DG28 | K69: Emergency | L69: Emergency Walk-in | M69: 44900 | N69: 6150 | O69: 10500 | P69: 0 | Q69: 62550 | R69: IP04 | S69: Approved | T69: 16540 | U69: 5 | V69: Yes | W69: 46164 | X69: Yes | Y69: No | Z69: Improved
A70: V10069 | B70: P2597 | C70: 46139 | D70: 09:15 | E70: Attended | F70: 46139 | G70: 46148 | H70: D04 | I70: DR121 | J70: DG09 | K70: Emergency | L70: Doctor Referral | M70: 80900 | N70: 8200 | O70: 9050 | P70: 54000 | Q70: 153650 | R70: IP03 | S70: Approved | T70: 24250 | U70: 4 | V70: Yes | W70: 46168 | X70: Yes | Y70: No | Z70: Improved
A71: V10070 | B71: P2167 | C71: 46147 | D71: 15:15 | E71: Rescheduled | H71: D03 | I71: DR114 | J71: DG05 | K71: Inpatient | L71: Emergency Walk-in | R71: IP06 | S71: Not Applicable | V71: No | X71: Not Required | Z71: Not Treated
A72: V10071 | B72: P2218 | C72: 46063 | D72: 16:30 | E72: Canceled | H72: D06 | I72: DR131 | J72: DG15 | K72: Surgery | L72: Emergency Walk-in | R72: IP03 | S72: Not Applicable | V72: No | X72: Not Required | Z72: Not Treated
A73: V10072 | B73: P2042 | C73: 46118 | D73: 12:30 | E73: Attended | F73: 46118 | G73: 46120 | H73: D07 | I73: DR137 | J73: DG17 | K73: Inpatient | L73: Scheduled Appointment | M73: 6700 | N73: 750 | O73: 950 | P73: 6000 | Q73: 16200 | R73: IP05 | S73: Not Applicable | T73: 16200 | U73: 4 | V73: No | X73: Not Required | Y73: No | Z73: Recovered
A74: V10073 | B74: P2346 | C74: 46056 | D74: 10:45 | E74: Attended | F74: 46056 | G74: 46056 | H74: D09 | I74: DR152 | J74: DG24 | K74: Inpatient | L74: Doctor Referral | M74: 6800 | N74: 950 | O74: 1300 | P74: 0 | Q74: 11550 | R74: IP02 | S74: Pending | T74: 4740 | U74: 4 | V74: Yes | W74: 46063 | X74: No | Y74: No | Z74: Stable
A75: V10074 | B75: P2317 | C75: 46166 | D75: 09:15 | E75: Rescheduled | H75: D08 | I75: DR143 | J75: DG19 | K75: Inpatient | L75: Scheduled Appointment | R75: IP05 | S75: Not Applicable | V75: No | X75: Not Required | Z75: Not Treated
A76: V10075 | B76: P2535 | C76: 46151 | D76: 08:00 | E76: Attended | F76: 46151 | G76: 46153 | H76: D04 | I76: DR122 | J76: DG08 | K76: Inpatient | L76: Transfer from Clinic | M76: 8000 | N76: 1350 | O76: 1350 | P76: 12000 | Q76: 25200 | R76: IP04 | S76: Approved | T76: 7200 | U76: 3 | V76: Yes | W76: 46173 | X76: No | Y76: No | Z76: Stable
A77: V10076 | B77: P2102 | C77: 46059 | D77: 10:30 | E77: Attended | F77: 46059 | G77: 46059 | H77: D07 | I77: DR139 | J77: DG18 | K77: Outpatient | L77: Transfer from Clinic | M77: 37200 | N77: 4100 | O77: 4250 | P77: 0 | Q77: 47350 | R77: IP01 | S77: Pending | T77: 21610 | U77: 3 | V77: Yes | W77: 46079 | X77: No | Y77: Yes | Z77: Improved
A78: V10077 | B78: P2118 | C78: 46141 | D78: 16:45 | E78: Attended | F78: 46141 | G78: 46141 | H78: D05 | I78: DR127 | J78: DG10 | K78: Outpatient | L78: Scheduled Appointment | M78: 5200 | N78: 700 | O78: 1150 | P78: 0 | Q78: 8550 | R78: IP02 | S78: Approved | T78: 3690 | U78: 5 | V78: Yes | W78: 46158 | X78: Yes | Y78: No | Z78: Against Medical Advice
A79: V10078 | B79: P2569 | C79: 46141 | D79: 17:30 | E79: Attended | F79: 46141 | G79: 46148 | H79: D06 | I79: DR131 | J79: DG14 | K79: Surgery | L79: Scheduled Appointment | M79: 64600 | N79: 10600 | O79: 10150 | P79: 24500 | Q79: 110650 | R79: IP05 | S79: Not Applicable | T79: 110650 | U79: 3 | V79: Yes | W79: 46168 | X79: Yes | Y79: Yes | Z79: Recovered
A80: V10079 | B80: P2570 | C80: 46076 | D80: 17:30 | E80: Cancelled | H80: D01 | I80: DR104 | J80: DG30 | K80: Outpatient | L80: Scheduled Appointment | R80: IP03 | S80: Not Applicable | V80: No | X80: Not Required | Z80: Not Treated
A81: V10080 | B81: P2252 | C81: 46110 | D81: 11:45 | E81: Rescheduled | H81: D08 | I81: DR145 | J81: DG21 | K81: Outpatient | L81: Scheduled Appointment | R81: IP02 | S81: Not Applicable | V81: No | X81: Not Required | Z81: Not Treated
A82: V10081 | B82: P2003 | C82: 46025 | D82: 10:45 | E82: Attended | F82: 46026 | G82: 46029 | H82: D08 | I82: DR143 | J82: DG20 | K82: Emergency | L82: Emergency Walk-in | M82: 60200 | N82: 5000 | O82: 13550 | P82: 13500 | Q82: 93050 | R82: IP04 | S82: Approved | T82: 24160 | U82: 4 | V82: No | X82: Not Required | Y82: No | Z82: Stable
A83: V10082 | B83: P2198 | C83: 46028 | D83: 12:30 | E83: Attended | F83: 46028 | G83: 46029 | H83: D04 | I83: DR120 | J83: DG08 | K83: Emergency | L83: Scheduled Appointment | M83: 8000 | N83: 1050 | O83: 1250 | P83: 3500 | Q83: 14600 | R83: IP03 | S83: Approved | T83: 3390 | U83: 5 | V83: Yes | W83: 46036 | X83: Yes | Y83: No | Z83: Recovered
A84: V10083 | B84: P2580 | C84: 46167 | D84: 10:00 | E84: Attended | F84: 46167 | G84: 46176 | H84: D09 | I84: DR153 | J84: DG22 | K84: Emergency | L84: Doctor Referral | M84: 34300 | N84: 6050 | O84: 6900 | P84: 54000 | Q84: 103250 | R84: IP02 | S84: Approved | T84: 36840 | U84: 2 | V84: Yes | W84: 46189 | X84: Yes | Y84: No | Z84: Recovered
A85: V10084 | B85: P2531 | C85: 46155 | D85: 08:15 | E85: Attended | F85: 46155 | G85: 46156 | H85: D07 | I85: DR139 | J85: DG16 | K85: Surgery | L85: Emergency Walk-in | M85: 11200 | N85: 1100 | O85: 1250 | P85: 6000 | Q85: 21350 | R85: IP05 | S85: Not Applicable | T85: 21350 | U85: 5 | V85: No | X85: Not Required | Y85: No | Z85: Stable
A86: V10085 | B86: P2100 | C86: 46029 | D86: 17:30 | E86: Missed | H86: D02 | I86: DR110 | J86: DG01 | K86: Outpatient | L86: Emergency Walk-in | R86: IP01 | S86: Not Applicable | V86: No | X86: Not Required | Z86: Not Treated
A87: V10086 | B87: P2342 | C87: 46041 | D87: 17:45 | E87: Attended | F87: 46041 | G87: 46046 | H87: D07 | I87: DR138 | J87: DG17 | K87: Inpatient | L87: Scheduled Appointment | M87: 5200 | N87: 900 | O87: 1050 | P87: 15000 | Q87: 24650 | R87: IP01 | S87: Pending | T87: 11390 | U87: 1 | V87: Yes | W87: 46062 | X87: Yes | Y87: Yes | Z87: Recovered
A88: V10087 | B88: P2239 | C88: 46025 | D88: 15:45 | E88: Attended | F88: 46025 | G88: 46026 | H88: D09 | I88: DR154 | J88: DG24 | K88: Inpatient | L88: Scheduled Appointment | M88: 9000 | N88: 1550 | O88: 1950 | P88: 4500 | Q88: 17800 | R88: IP03 | S88: Approved | T88: 3870 | U88: 3 | V88: Yes | W88: 46033 | X88: Yes | Y88: Yes | Z88: Recovered
A89: V10088 | B89: P2456 | C89: 46034 | D89: 08:15 | E89: Attended | F89: 46034 | G89: 46039 | H89: D03 | I89: DR114 | J89: DG04 | K89: Inpatient | L89: Transfer from Clinic | M89: 65400 | N89: 7250 | O89: 9900 | P89: 17500 | Q89: 101050 | R89: IP07 | S89: Approved | T89: 55780 | U89: 5 | V89: Yes | W89: 46048 | X89: Yes | Y89: No | Z89: Improved
A90: V10089 | B90: P2071 | C90: 46144 | D90: 15:30 | E90: No Show | H90: D05 | I90: DR130 | J90: DG12 | K90: Outpatient | L90: Emergency Walk-in | R90: IP03 | S90: Not Applicable | V90: No | X90: Not Required | Z90: Not Treated
A91: V10090 | B91: P2167 | C91: 46149 | D91: 11:00 | E91: Attended | F91: 46149 | G91: 46161 | H91: D03 | I91: DR113 | J91: DG04 | K91: Emergency | L91: Emergency Walk-in | M91: 70800 | N91: 11450 | O91: 15650 | P91: 54000 | Q91: 154400 | R91: IP01 | S91: Approved | T91: 69780 | U91: 1 | V91: No | X91: Not Required | Y91: Yes | Z91: Recovered
A92: V10091 | B92: P2369 | C92: 46073 | D92: 11:30 | E92: Attended | F92: 46073 | G92: 46080 | H92: D02 | I92: DR107 | J92: DG02 | K92: Emergency | L92: Scheduled Appointment | M92: 59100 | N92: 10100 | O92: 6100 | P92: 21000 | Q92: 97800 | R92: IP02 | S92: Pending | T92: 34930 | U92: 4 | V92: Yes | W92: 46101 | X92: Yes | Y92: No | Z92: Improved
A93: V10092 | B93: P2445 | C93: 46053 | D93: 10:15 | E93: Missed | H93: D10 | I93: DR155 | J93: DG27 | K93: Emergency | L93: Emergency Walk-in | R93: IP04 | S93: Not Applicable | V93: No | X93: Not Required | Z93: Not Treated
A94: V10093 | B94: P2251 | C94: 46071 | D94: 16:30 | E94: No Show | H94: D01 | I94: DR105 | J94: DG29 | K94: Inpatient | L94: Scheduled Appointment | R94: IP07 | S94: Not Applicable | V94: No | X94: Not Required | Z94: Not Treated
A95: V10094 | B95: P2521 | C95: 46076 | D95: 09:45 | E95: No Show | H95: D01 | I95: DR104 | J95: DG30 | K95: Emergency | L95: Scheduled Appointment | R95: IP07 | S95: Not Applicable | V95: No | X95: Not Required | Z95: Not Treated
A96: V10095 | B96: P2522 | C96: 46141 | D96: 10:30 | E96: Attended | F96: 46142 | G96: 46144 | H96: D05 | I96: DR129 | J96: DG11 | K96: Inpatient | L96: Emergency Walk-in | M96: 27800 | N96: 3850 | O96: 5450 | P96: 12000 | Q96: 51100 | R96: IP04 | S96: Approved | T96: 13680 | U96: 4 | V96: No | X96: Not Required | Y96: No | Z96: Stable
A97: V10096 | B97: P2564 | C97: 46098 | D97: 15:30 | E97: Attended | F97: 46098 | G97: 46099 | H97: D02 | I97: DR107 | J97: DG02 | K97: Outpatient | L97: Emergency Walk-in | M97: 45500 | N97: 5400 | O97: 5800 | P97: 3000 | Q97: 61200 | R97: IP02 | S97: Approved | T97: 22120 | U97: 5 | V97: Yes | W97: 46114 | X97: Yes | Y97: No | Z97: Recovered
A98: V10097 | B98: P2202 | C98: 46100 | D98: 12:15 | E98: Attended | F98: 46100 | G98: 46107 | H98: D08 | I98: DR145 | J98: DG21 | K98: Surgery | L98: Transfer from Clinic | M98: 50700 | N98: 5800 | O98: 12650 | P98: 31500 | Q98: 101450 | R98: IP05 | S98: Not Applicable | T98: 101450 | U98: 3 | V98: Yes | W98: 46114 | X98: Yes | Y98: No | Z98: Recovered
A99: V10098 | B99: P2566 | C99: 46141 | D99: 13:00 | E99: Attended | F99: 46142 | G99: 46142 | H99: D10 | I99: DR160 | J99: DG25 | K99: Outpatient | L99: Scheduled Appointment | M99: 22400 | N99: 3100 | O99: 2650 | P99: 0 | Q99: 29150 | R99: IP06 | S99: Approved | T99: 9150 | U99: 5 | V99: No | X99: Not Required | Y99: No | Z99: Improved
A100: V10099 | B100: P2307 | C100: 46168 | D100: 08:15 | E100: Attended | F100: 46169 | G100: 46174 | H100: D05 | I100: DR125 | J100: DG11 | K100: Surgery | L100: Emergency Walk-in | M100: 27400 | N100: 2750 | O100: 4350 | P100: 30000 | Q100: 65700 | R100: IP02 | S100: Approved | T100: 23700 | U100: 4 | V100: Yes | W100: 46188 | X100: Yes | Y100: No | Z100: Improved
...

Sheet Prepared_Visits
A1: Visit ID | B1: Patient ID | C1: Appointment Date | D1: Appointment Time | E1: Appointment Status | F1: Admission Date | G1: Discharge Date | H1: Department ID | I1: Doctor ID | J1: Diagnosis Code | K1: Visit Type | L1: Admission Source | M1: Treatment Cost | N1: Lab Cost | O1: Medicine Cost | P1: Room Cost | Q1: Total Bill | R1: Insurance Plan ID | S1: Claim Status | T1: Patient Payable | U1: Patient Satisfaction | V1: Follow Up Required | W1: Follow Up Date | X1: Follow Up Completed | Y1: Readmitted Within 30 Days | Z1: Discharge Outcome | AA1: DepartmentName | AB1: DiagnosisName | AC1: DiseaseCategory | AD1: InsuranceType | AE1: HospitalServiceFee | AF1: FinalBill | AG1: SatisfactionGroup
A2: V10001 | B2: P2181 | C2: 46071 | D2: 12:45 | E2: Cancelled | H2: D09 | I2: DR152 | J2: DG22 | K2: Outpatient | L2: Doctor Referral | R2: IP06 | S2: Not Applicable | V2: No | X2: Not Required | Z2: Not Treated | AA2: =VLOOKUP(H2,Departments!$A:$B,2,0) -> Pulmonology | AB2: =VLOOKUP(J2,Diagnosis_Guide!$A:$B,2,0) -> Pneumonia | AC2: =VLOOKUP(J2,Diagnosis_Guide!$A:$C,3,0) -> Respiratory | AD2: =VLOOKUP(R2,Insurance_Plans!$A:$C,3,0) -> Public | AE2: =IF(Q2="","",Q2*0.05) | AF2: =IF(Q2="","",Q2+AE2) | AG2: =IF(U2="","Not Available",IF(U2>=4,"High",IF(U2=3,"Medium","Low"))) -> Not Available
A3: V10002 | B3: P2449 | C3: 46032 | D3: 11:00 | E3: Attended | F3: 46032 | G3: 46034 | H3: D09 | I3: DR150 | J3: DG24 | K3: Inpatient | L3: Emergency Walk-in | M3: 7600 | N3: 1350 | O3: 1700 | P3: 5000 | Q3: 17450 | R3: IP01 | S3: Approved | T3: 8150 | U3: 2 | V3: No | X3: Not Required | Y3: Yes | Z3: Improved | AA3: =VLOOKUP(H3,Departments!$A:$B,2,0) -> Pulmonology | AB3: =VLOOKUP(J3,Diagnosis_Guide!$A:$B,2,0) -> Acute Bronchitis | AC3: =VLOOKUP(J3,Diagnosis_Guide!$A:$C,3,0) -> Respiratory | AD3: =VLOOKUP(R3,Insurance_Plans!$A:$C,3,0) -> Public | AE3: =IF(Q3="","",Q3*0.05) -> 872.5 | AF3: =IF(Q3="","",Q3+AE3) -> 18322.5 | AG3: =IF(U3="","Not Available",IF(U3>=4,"High",IF(U3=3,"Medium","Low"))) -> Low
A4: V10003 | B4: P2550 | C4: 46082 | D4: 09:00 | E4: Attended | F4: 46082 | G4: 46082 | H4: D04 | I4: DR123 | J4: DG08 | K4: Inpatient | L4: Doctor Referral | M4: 6300 | N4: 900 | O4: 650 | P4: 0 | Q4: 9650 | R4: IP04 | S4: Pending | T4: 3310 | U4: 5 | V4: No | X4: Not Required | Y4: No | Z4: Improved | AA4: =VLOOKUP(H4,Departments!$A:$B,2,0) -> Orthopedics | AB4: =VLOOKUP(J4,Diagnosis_Guide!$A:$B,2,0) -> Joint Pain | AC4: =VLOOKUP(J4,Diagnosis_Guide!$A:$C,3,0) -> Musculoskeletal | AD4: =VLOOKUP(R4,Insurance_Plans!$A:$C,3,0) -> Employer | AE4: =IF(Q4="","",Q4*0.05) -> 482.5 | AF4: =IF(Q4="","",Q4+AE4) -> 10132.5 | AG4: =IF(U4="","Not Available",IF(U4>=4,"High",IF(U4=3,"Medium","Low"))) -> High
A5: V10004 | B5: P2226 | C5: 46132 | D5: 13:45 | E5: Attended | F5: 46132 | G5: 46137 | H5: D02 | I5: DR108 | J5: DG02 | K5: Surgery | L5: Scheduled Appointment | M5: 59900 | N5: 6800 | O5: 7050 | P5: 15000 | Q5: 89950 | R5: IP05 | S5: Not Applicable | T5: 89950 | U5: 5 | V5: Yes | W5: 46149 | X5: Yes | Y5: No | Z5: Recovered | AA5: =VLOOKUP(H5,Departments!$A:$B,2,0) -> Cardiology | AB5: =VLOOKUP(J5,Diagnosis_Guide!$A:$B,2,0) -> Heart Failure | AC5: =VLOOKUP(J5,Diagnosis_Guide!$A:$C,3,0) -> Cardiovascular | AD5: =VLOOKUP(R5,Insurance_Plans!$A:$C,3,0) -> Self-Pay | AE5: =IF(Q5="","",Q5*0.05) -> 4497.5 | AF5: =IF(Q5="","",Q5+AE5) -> 94447.5 | AG5: =IF(U5="","Not Available",IF(U5>=4,"High",IF(U5=3,"Medium","Low"))) -> High
A6: V10005 | B6: P2017 | C6: 46024 | D6: 08:15 | E6: Cancelled | H6: D09 | I6: DR149 | J6: DG24 | K6: Inpatient | L6: Emergency Walk-in | R6: IP06 | S6: Not Applicable | V6: No | X6: Not Required | Z6: Not Treated | AA6: =VLOOKUP(H6,Departments!$A:$B,2,0) -> Pulmonology | AB6: =VLOOKUP(J6,Diagnosis_Guide!$A:$B,2,0) -> Acute Bronchitis | AC6: =VLOOKUP(J6,Diagnosis_Guide!$A:$C,3,0) -> Respiratory | AD6: =VLOOKUP(R6,Insurance_Plans!$A:$C,3,0) -> Public | AE6: =IF(Q6="","",Q6*0.05) | AF6: =IF(Q6="","",Q6+AE6) | AG6: =IF(U6="","Not Available",IF(U6>=4,"High",IF(U6=3,"Medium","Low"))) -> Not Available
A7: V10006 | B7: P2488 | C7: 46059 | D7: 12:45 | E7: Attended | F7: 46059 | G7: 46067 | H7: D08 | I7: DR144 | J7: DG21 | K7: Surgery | L7: Scheduled Appointment | M7: 63500 | N7: 8950 | O7: 7200 | P7: 28000 | Q7: 109450 | R7: IP02 | S7: Approved | T7: 39010 | U7: 3 | V7: Yes | W7: 46075 | X7: No | Y7: No | Z7: Stable | AA7: =VLOOKUP(H7,Departments!$A:$B,2,0) -> Nephrology | AB7: =VLOOKUP(J7,Diagnosis_Guide!$A:$B,2,0) -> Dialysis Complication | AC7: =VLOOKUP(J7,Diagnosis_Guide!$A:$C,3,0) -> Renal | AD7: =VLOOKUP(R7,Insurance_Plans!$A:$C,3,0) -> Private | AE7: =IF(Q7="","",Q7*0.05) -> 5472.5 | AF7: =IF(Q7="","",Q7+AE7) -> 114922.5 | AG7: =IF(U7="","Not Available",IF(U7>=4,"High",IF(U7=3,"Medium","Low"))) -> Medium
A8: V10007 | B8: P2214 | C8: 46051 | D8: 10:45 | E8: Attended | F8: 46051 | G8: 46051 | H8: D05 | I8: DR126 | J8: DG11 | K8: Outpatient | L8: Scheduled Appointment | M8: 20100 | N8: 3250 | O8: 4300 | P8: 0 | Q8: 28450 | R8: IP01 | S8: Approved | T8: 13100 | U8: 4 | V8: No | X8: Not Required | Y8: No | Z8: Recovered | AA8: =VLOOKUP(H8,Departments!$A:$B,2,0) -> General Medicine | AB8: =VLOOKUP(J8,Diagnosis_Guide!$A:$B,2,0) -> Diabetes Complication | AC8: =VLOOKUP(J8,Diagnosis_Guide!$A:$C,3,0) -> Endocrine/General | AD8: =VLOOKUP(R8,Insurance_Plans!$A:$C,3,0) -> Public | AE8: =IF(Q8="","",Q8*0.05) -> 1422.5 | AF8: =IF(Q8="","",Q8+AE8) -> 29872.5 | AG8: =IF(U8="","Not Available",IF(U8>=4,"High",IF(U8=3,"Medium","Low"))) -> High
A9: V10008 | B9: P2334 | C9: 46106 | D9: 11:00 | E9: Attended | F9: 46106 | G9: 46106 | H9: D05 | I9: DR130 | J9: DG10 | K9: Outpatient | L9: Scheduled Appointment | M9: 5800 | N9: 750 | O9: 1000 | P9: 0 | Q9: 8350 | R9: IP06 | S9: Approved | T9: 2910 | U9: 5 | V9: No | X9: Not Required | Y9: No | Z9: Improved | AA9: =VLOOKUP(H9,Departments!$A:$B,2,0) -> General Medicine | AB9: =VLOOKUP(J9,Diagnosis_Guide!$A:$B,2,0) -> Fever Investigation | AC9: =VLOOKUP(J9,Diagnosis_Guide!$A:$C,3,0) -> Infectious/General | AD9: =VLOOKUP(R9,Insurance_Plans!$A:$C,3,0) -> Public | AE9: =IF(Q9="","",Q9*0.05) -> 417.5 | AF9: =IF(Q9="","",Q9+AE9) -> 8767.5 | AG9: =IF(U9="","Not Available",IF(U9>=4,"High",IF(U9=3,"Medium","Low"))) -> High
A10: V10009 | B10: P2344 | C10: 46168 | D10: 08:30 | E10: Attended | F10: 46168 | G10: 46172 | H10: D03 | I10: DR118 | J10: DG06 | K10: Emergency | L10: Emergency Walk-in | M10: 42600 | N10: 6150 | O10: 8150 | P10: 12000 | Q10: 69900 | R10: IP04 | S10: Approved | T10: 18380 | U10: 3 | V10: Yes | W10: 46185 | X10: No | Y10: No | Z10: Stable | AA10: =VLOOKUP(H10,Departments!$A:$B,2,0) -> Neurology | AB10: =VLOOKUP(J10,Diagnosis_Guide!$A:$B,2,0) -> Seizure Episode | AC10: =VLOOKUP(J10,Diagnosis_Guide!$A:$C,3,0) -> Neurological | AD10: =VLOOKUP(R10,Insurance_Plans!$A:$C,3,0) -> Employer | AE10: =IF(Q10="","",Q10*0.05) -> 3495 | AF10: =IF(Q10="","",Q10+AE10) -> 73395 | AG10: =IF(U10="","Not Available",IF(U10>=4,"High",IF(U10=3,"Medium","Low"))) -> Medium
A11: V10010 | B11: P2253 | C11: 46171 | D11: 11:15 | E11: Cancelled | H11: D02 | I11: DR110 | J11: DG03 | K11: Outpatient | L11: Doctor Referral | R11: IP04 | S11: Not Applicable | V11: No | X11: Not Required | Z11: Not Treated | AA11: =VLOOKUP(H11,Departments!$A:$B,2,0) -> Cardiology | AB11: =VLOOKUP(J11,Diagnosis_Guide!$A:$B,2,0) -> Hypertension Crisis | AC11: =VLOOKUP(J11,Diagnosis_Guide!$A:$C,3,0) -> Cardiovascular | AD11: =VLOOKUP(R11,Insurance_Plans!$A:$C,3,0) -> Employer | AE11: =IF(Q11="","",Q11*0.05) | AF11: =IF(Q11="","",Q11+AE11) | AG11: =IF(U11="","Not Available",IF(U11>=4,"High",IF(U11=3,"Medium","Low"))) -> Not Available
A12: V10011 | B12: P2517 | C12: 46123 | D12: 15:00 | E12: Attended | F12: 46123 | G12: 46123 | H12: D02 | I12: DR111 | J12: DG02 | K12: Outpatient | L12: Scheduled Appointment | M12: 43000 | N12: 5000 | O12: 5850 | P12: 0 | Q12: 55850 | R12: IP07 | S12: Approved | T12: 30920 | V12: Yes | W12: 46132 | X12: No | Y12: No | Z12: Improved | AA12: =VLOOKUP(H12,Departments!$A:$B,2,0) -> Cardiology | AB12: =VLOOKUP(J12,Diagnosis_Guide!$A:$B,2,0) -> Heart Failure | AC12: =VLOOKUP(J12,Diagnosis_Guide!$A:$C,3,0) -> Cardiovascular | AD12: =VLOOKUP(R12,Insurance_Plans!$A:$C,3,0) -> Community | AE12: =IF(Q12="","",Q12*0.05) -> 2792.5 | AF12: =IF(Q12="","",Q12+AE12) -> 58642.5 | AG12: =IF(U12="","Not Available",IF(U12>=4,"High",IF(U12=3,"Medium","Low"))) -> Not Available
A13: V10012 | B13: P2380 | C13: 46023 | D13: 09:45 | E13: Cancelled | H13: D07 | I13: DR142 | J13: DG16 | K13: Outpatient | L13: Emergency Walk-in | R13: IP03 | S13: Not Applicable | V13: No | X13: Not Required | Z13: Not Treated | AA13: =VLOOKUP(H13,Departments!$A:$B,2,0) -> Pediatrics | AB13: =VLOOKUP(J13,Diagnosis_Guide!$A:$B,2,0) -> Pediatric Asthma | AC13: =VLOOKUP(J13,Diagnosis_Guide!$A:$C,3,0) -> Pediatric | AD13: =VLOOKUP(R13,Insurance_Plans!$A:$C,3,0) -> Private | AE13: =IF(Q13="","",Q13*0.05) | AF13: =IF(Q13="","",Q13+AE13) | AG13: =IF(U13="","Not Available",IF(U13>=4,"High",IF(U13=3,"Medium","Low"))) -> Not Available
A14: V10013 | B14: P2556 | C14: 46043 | D14: 17:30 | E14: Attended | F14: 46043 | G14: 46043 | H14: D08 | I14: DR144 | J14: DG19 | K14: Outpatient | L14: Transfer from Clinic | M14: 27500 | N14: 3200 | O14: 3450 | P14: 0 | Q14: 35950 | R14: IP04 | S14: Approved | T14: 9890 | U14: 5 | V14: No | X14: Not Required | Y14: No | Z14: Recovered | AA14: =VLOOKUP(H14,Departments!$A:$B,2,0) -> Nephrology | AB14: =VLOOKUP(J14,Diagnosis_Guide!$A:$B,2,0) -> Kidney Stone | AC14: =VLOOKUP(J14,Diagnosis_Guide!$A:$C,3,0) -> Renal | AD14: =VLOOKUP(R14,Insurance_Plans!$A:$C,3,0) -> Employer | AE14: =IF(Q14="","",Q14*0.05) -> 1797.5 | AF14: =IF(Q14="","",Q14+AE14) -> 37747.5 | AG14: =IF(U14="","Not Available",IF(U14>=4,"High",IF(U14=3,"Medium","Low"))) -> High
A15: V10014 | B15: P2215 | C15: 46105 | D15: 13:30 | E15: Attended | F15: 46105 | G15: 46107 | H15: D10 | I15: DR156 | J15: DG25 | K15: Inpatient | L15: Doctor Referral | M15: 22000 | N15: 2850 | O15: 3950 | P15: 5000 | Q15: 36300 | R15: IP03 | S15: Approved | T15: 6650 | U15: 5 | V15: No | X15: Not Required | Y15: No | Z15: Stable | AA15: =VLOOKUP(H15,Departments!$A:$B,2,0) -> Obstetrics | AB15: =VLOOKUP(J15,Diagnosis_Guide!$A:$B,2,0) -> Antenatal Complication | AC15: =VLOOKUP(J15,Diagnosis_Guide!$A:$C,3,0) -> Maternal Health | AD15: =VLOOKUP(R15,Insurance_Plans!$A:$C,3,0) -> Private | AE15: =IF(Q15="","",Q15*0.05) -> 1815 | AF15: =IF(Q15="","",Q15+AE15) -> 38115 | AG15: =IF(U15="","Not Available",IF(U15>=4,"High",IF(U15=3,"Medium","Low"))) -> High
A16: V10015 | B16: P2068 | C16: 46045 | D16: 09:45 | E16: Cancelled | H16: D04 | I16: DR122 | J16: DG09 | K16: Surgery | L16: Doctor Referral | R16: IP03 | S16: Not Applicable | V16: No | X16: Not Required | Z16: Not Treated | AA16: =VLOOKUP(H16,Departments!$A:$B,2,0) -> Orthopedics | AB16: =VLOOKUP(J16,Diagnosis_Guide!$A:$B,2,0) -> Spinal Injury | AC16: =VLOOKUP(J16,Diagnosis_Guide!$A:$C,3,0) -> Musculoskeletal | AD16: =VLOOKUP(R16,Insurance_Plans!$A:$C,3,0) -> Private | AE16: =IF(Q16="","",Q16*0.05) | AF16: =IF(Q16="","",Q16+AE16) | AG16: =IF(U16="","Not Available",IF(U16>=4,"High",IF(U16=3,"Medium","Low"))) -> Not Available
A17: V10016 | B17: P2115 | C17: 46061 | D17: 11:00 | E17: Attended | F17: 46061 | G17: 46064 | H17: D09 | I17: DR152 | J17: DG22 | K17: Surgery | L17: Emergency Walk-in | M17: 39000 | N17: 3850 | O17: 4050 | P17: 9000 | Q17: 58400 | R17: IP05 | S17: Not Applicable | T17: 58400 | U17: 5 | V17: Yes | W17: 46076 | X17: Yes | Y17: No | Z17: Improved | AA17: =VLOOKUP(H17,Departments!$A:$B,2,0) -> Pulmonology | AB17: =VLOOKUP(J17,Diagnosis_Guide!$A:$B,2,0) -> Pneumonia | AC17: =VLOOKUP(J17,Diagnosis_Guide!$A:$C,3,0) -> Respiratory | AD17: =VLOOKUP(R17,Insurance_Plans!$A:$C,3,0) -> Self-Pay | AE17: =IF(Q17="","",Q17*0.05) -> 2920 | AF17: =IF(Q17="","",Q17+AE17) -> 61320 | AG17: =IF(U17="","Not Available",IF(U17>=4,"High",IF(U17=3,"Medium","Low"))) -> High
A18: V10017 | B18: P2581 | C18: 46066 | D18: 12:15 | E18: Attended | F18: 46066 | G18: 46074 | H18: D02 | I18: DR109 | J18: DG02 | K18: Surgery | L18: Scheduled Appointment | M18: 55900 | N18: 5400 | O18: 13350 | P18: 48000 | Q18: 123850 | R18: IP02 | S18: Rejected | T18: 44050 | U18: 3 | V18: No | X18: Not Required | Y18: No | Z18: Recovered | AA18: =VLOOKUP(H18,Departments!$A:$B,2,0) -> Cardiology | AB18: =VLOOKUP(J18,Diagnosis_Guide!$A:$B,2,0) -> Heart Failure | AC18: =VLOOKUP(J18,Diagnosis_Guide!$A:$C,3,0) -> Cardiovascular | AD18: =VLOOKUP(R18,Insurance_Plans!$A:$C,3,0) -> Private | AE18: =IF(Q18="","",Q18*0.05) -> 6192.5 | AF18: =IF(Q18="","",Q18+AE18) -> 130042.5 | AG18: =IF(U18="","Not Available",IF(U18>=4,"High",IF(U18=3,"Medium","Low"))) -> Medium
A19: V10018 | B19: P2379 | C19: 46031 | D19: 13:30 | E19: Attended | F19: 46031 | G19: 46033 | H19: D04 | I19: DR123 | J19: DG08 | K19: Inpatient | L19: Transfer from Clinic | M19: 10000 | N19: 1550 | O19: 2400 | P19: 7000 | Q19: 22750 | R19: IP01 | S19: Rejected | T19: 10540 | U19: 4 | V19: No | X19: Not Required | Y19: No | Z19: Recovered | AA19: =VLOOKUP(H19,Departments!$A:$B,2,0) -> Orthopedics | AB19: =VLOOKUP(J19,Diagnosis_Guide!$A:$B,2,0) -> Joint Pain | AC19: =VLOOKUP(J19,Diagnosis_Guide!$A:$C,3,0) -> Musculoskeletal | AD19: =VLOOKUP(R19,Insurance_Plans!$A:$C,3,0) -> Public | AE19: =IF(Q19="","",Q19*0.05) -> 1137.5 | AF19: =IF(Q19="","",Q19+AE19) -> 23887.5 | AG19: =IF(U19="","Not Available",IF(U19>=4,"High",IF(U19=3,"Medium","Low"))) -> High
A20: V10019 | B20: P2151 | C20: 46136 | D20: 13:00 | E20: Attended | F20: 46136 | G20: 46144 | H20: D09 | I20: DR154 | J20: DG23 | K20: Emergency | L20: Doctor Referral | M20: 63500 | N20: 6500 | O20: 9750 | P20: 28000 | Q20: 108550 | R20: IP01 | S20: Approved | T20: 49150 | V20: Yes | W20: 46154 | X20: No | Y20: No | Z20: Improved | AA20: =VLOOKUP(H20,Departments!$A:$B,2,0) -> Pulmonology | AB20: =VLOOKUP(J20,Diagnosis_Guide!$A:$B,2,0) -> COPD Exacerbation | AC20: =VLOOKUP(J20,Diagnosis_Guide!$A:$C,3,0) -> Respiratory | AD20: =VLOOKUP(R20,Insurance_Plans!$A:$C,3,0) -> Public | AE20: =IF(Q20="","",Q20*0.05) -> 5427.5 | AF20: =IF(Q20="","",Q20+AE20) -> 113977.5 | AG20: =IF(U20="","Not Available",IF(U20>=4,"High",IF(U20=3,"Medium","Low"))) -> Not Available
A21: V10020 | B21: P2525 | C21: 46104 | D21: 17:00 | E21: Cancelled | H21: D03 | I21: DR116 | J21: DG06 | K21: Outpatient | L21: Scheduled Appointment | R21: IP03 | S21: Not Applicable | V21: No | X21: Not Required | Z21: Not Treated | AA21: =VLOOKUP(H21,Departments!$A:$B,2,0) -> Neurology | AB21: =VLOOKUP(J21,Diagnosis_Guide!$A:$B,2,0) -> Seizure Episode | AC21: =VLOOKUP(J21,Diagnosis_Guide!$A:$C,3,0) -> Neurological | AD21: =VLOOKUP(R21,Insurance_Plans!$A:$C,3,0) -> Private | AE21: =IF(Q21="","",Q21*0.05) | AF21: =IF(Q21="","",Q21+AE21) | AG21: =IF(U21="","Not Available",IF(U21>=4,"High",IF(U21=3,"Medium","Low"))) -> Not Available
A22: V10021 | B22: P2396 | C22: 46111 | D22: 13:30 | E22: Rescheduled | H22: D06 | I22: DR133 | J22: DG13 | K22: Surgery | L22: Scheduled Appointment | R22: IP04 | S22: Not Applicable | V22: No | X22: Not Required | Z22: Not Treated | AA22: =VLOOKUP(H22,Departments!$A:$B,2,0) -> Surgery | AB22: =VLOOKUP(J22,Diagnosis_Guide!$A:$B,2,0) -> Appendicitis Surgery | AC22: =VLOOKUP(J22,Diagnosis_Guide!$A:$C,3,0) -> Surgical | AD22: =VLOOKUP(R22,Insurance_Plans!$A:$C,3,0) -> Employer | AE22: =IF(Q22="","",Q22*0.05) | AF22: =IF(Q22="","",Q22+AE22) | AG22: =IF(U22="","Not Available",IF(U22>=4,"High",IF(U22=3,"Medium","Low"))) -> Not Available
A23: V10022 | B23: P2426 | C23: 46064 | D23: 14:45 | E23: Attended | F23: 46064 | G23: 46068 | H23: D09 | I23: DR151 | J23: DG23 | K23: Inpatient | L23: Doctor Referral | M23: 54800 | N23: 9500 | O23: 10350 | P23: 18000 | Q23: 93850 | R23: IP01 | S23: Approved | T23: 42530 | U23: 5 | V23: No | X23: Not Required | Y23: No | Z23: Recovered | AA23: =VLOOKUP(H23,Departments!$A:$B,2,0) -> Pulmonology | AB23: =VLOOKUP(J23,Diagnosis_Guide!$A:$B,2,0) -> COPD Exacerbation | AC23: =VLOOKUP(J23,Diagnosis_Guide!$A:$C,3,0) -> Respiratory | AD23: =VLOOKUP(R23,Insurance_Plans!$A:$C,3,0) -> Public | AE23: =IF(Q23="","",Q23*0.05) -> 4692.5 | AF23: =IF(Q23="","",Q23+AE23) -> 98542.5 | AG23: =IF(U23="","Not Available",IF(U23>=4,"High",IF(U23=3,"Medium","Low"))) -> High
A24: V10023 | B24: P2044 | C24: 46172 | D24: 12:45 | E24: Attended | F24: 46172 | G24: 46184 | H24: D10 | I24: DR157 | J24: DG27 | K24: Inpatient | L24: Doctor Referral | M24: 103400 | N24: 16900 | O24: 17650 | P24: 42000 | Q24: 182450 | R24: IP03 | S24: Approved | T24: 28570 | U24: 3 | V24: Yes | W24: 46194 | X24: Yes | Y24: No | Z24: Recovered | AA24: =VLOOKUP(H24,Departments!$A:$B,2,0) -> Obstetrics | AB24: =VLOOKUP(J24,Diagnosis_Guide!$A:$B,2,0) -> Emergency C-Section | AC24: =VLOOKUP(J24,Diagnosis_Guide!$A:$C,3,0) -> Maternal Health | AD24: =VLOOKUP(R24,Insurance_Plans!$A:$C,3,0) -> Private | AE24: =IF(Q24="","",Q24*0.05) -> 9122.5 | AF24: =IF(Q24="","",Q24+AE24) -> 191572.5 | AG24: =IF(U24="","Not Available",IF(U24>=4,"High",IF(U24=3,"Medium","Low"))) -> Medium
A25: V10024 | B25: P2265 | C25: 46053 | D25: 13:00 | E25: No-show | H25: D09 | I25: DR152 | J25: DG22 | K25: Outpatient | L25: Emergency Walk-in | R25: IP06 | S25: Not Applicable | V25: No | X25: Not Required | Z25: Not Treated | AA25: =VLOOKUP(H25,Departments!$A:$B,2,0) -> Pulmonology | AB25: =VLOOKUP(J25,Diagnosis_Guide!$A:$B,2,0) -> Pneumonia | AC25: =VLOOKUP(J25,Diagnosis_Guide!$A:$C,3,0) -> Respiratory | AD25: =VLOOKUP(R25,Insurance_Plans!$A:$C,3,0) -> Public | AE25: =IF(Q25="","",Q25*0.05) | AF25: =IF(Q25="","",Q25+AE25) | AG25: =IF(U25="","Not Available",IF(U25>=4,"High",IF(U25=3,"Medium","Low"))) -> Not Available
A26: V10025 | B26: P2139 | C26: 46092 | D26: 13:45 | E26: Attended | F26: 46092 | G26: 46092 | H26: D04 | I26: DR119 | J26: DG08 | K26: Surgery | L26: Doctor Referral | M26: 7300 | N26: 1150 | O26: 950 | P26: 0 | Q26: 11200 | R26: IP01 | S26: Approved | T26: 5340 | U26: 5 | V26: No | X26: Not Required | Y26: No | Z26: Improved | AA26: =VLOOKUP(H26,Departments!$A:$B,2,0) -> Orthopedics | AB26: =VLOOKUP(J26,Diagnosis_Guide!$A:$B,2,0) -> Joint Pain | AC26: =VLOOKUP(J26,Diagnosis_Guide!$A:$C,3,0) -> Musculoskeletal | AD26: =VLOOKUP(R26,Insurance_Plans!$A:$C,3,0) -> Public | AE26: =IF(Q26="","",Q26*0.05) -> 560 | AF26: =IF(Q26="","",Q26+AE26) -> 11760 | AG26: =IF(U26="","Not Available",IF(U26>=4,"High",IF(U26=3,"Medium","Low"))) -> High
A27: V10026 | B27: P2148 | C27: 46095 | D27: 13:45 | E27: Attended | F27: 46095 | G27: 46097 | H27: D02 | I27: DR111 | J27: DG01 | K27: Surgery | L27: Doctor Referral | M27: 14800 | N27: 1500 | O27: 1900 | P27: 12000 | Q27: 32200 | R27: IP04 | S27: Pending | T27: 8950 | U27: 5 | V27: No | X27: Not Required | Y27: No | Z27: Stable | AA27: =VLOOKUP(H27,Departments!$A:$B,2,0) -> Cardiology | AB27: =VLOOKUP(J27,Diagnosis_Guide!$A:$B,2,0) -> Chest Pain | AC27: =VLOOKUP(J27,Diagnosis_Guide!$A:$C,3,0) -> Cardiovascular | AD27: =VLOOKUP(R27,Insurance_Plans!$A:$C,3,0) -> Employer | AE27: =IF(Q27="","",Q27*0.05) -> 1610 | AF27: =IF(Q27="","",Q27+AE27) -> 33810 | AG27: =IF(U27="","Not Available",IF(U27>=4,"High",IF(U27=3,"Medium","Low"))) -> High
A28: V10027 | B28: P2135 | C28: 46112 | D28: 12:30 | E28: Attended | F28: 46112 | G28: 46112 | H28: D01 | I28: DR104 | J28: DG28 | K28: Outpatient | L28: Emergency Walk-in | M28: 33000 | N28: 4950 | O28: 6700 | P28: 0 | Q28: 47150 | R28: IP02 | S28: Approved | T28: 17200 | U28: 4 | V28: No | X28: Not Required | Y28: No | Z28: Stable | AA28: =VLOOKUP(H28,Departments!$A:$B,2,0) -> Emergency | AB28: =VLOOKUP(J28,Diagnosis_Guide!$A:$B,2,0) -> Trauma Observation | AC28: =VLOOKUP(J28,Diagnosis_Guide!$A:$C,3,0) -> Emergency | AD28: =VLOOKUP(R28,Insurance_Plans!$A:$C,3,0) -> Private | AE28: =IF(Q28="","",Q28*0.05) -> 2357.5 | AF28: =IF(Q28="","",Q28+AE28) -> 49507.5 | AG28: =IF(U28="","Not Available",IF(U28>=4,"High",IF(U28=3,"Medium","Low"))) -> High
A29: V10028 | B29: P2526 | C29: 46053 | D29: 12:00 | E29: Attended | F29: 46053 | G29: 46058 | H29: D08 | I29: DR146 | J29: DG21 | K29: Inpatient | L29: Scheduled Appointment | M29: 42700 | N29: 7250 | O29: 5450 | P29: 17500 | Q29: 74400 | R29: IP01 | S29: Approved | T29: 33780 | U29: 4 | V29: Yes | W29: 46069 | X29: No | Y29: No | Z29: Stable | AA29: =VLOOKUP(H29,Departments!$A:$B,2,0) -> Nephrology | AB29: =VLOOKUP(J29,Diagnosis_Guide!$A:$B,2,0) -> Dialysis Complication | AC29: =VLOOKUP(J29,Diagnosis_Guide!$A:$C,3,0) -> Renal | AD29: =VLOOKUP(R29,Insurance_Plans!$A:$C,3,0) -> Public | AE29: =IF(Q29="","",Q29*0.05) -> 3720 | AF29: =IF(Q29="","",Q29+AE29) -> 78120 | AG29: =IF(U29="","Not Available",IF(U29>=4,"High",IF(U29=3,"Medium","Low"))) -> High
A30: V10029 | B30: P2593 | C30: 46078 | D30: 11:30 | E30: Attended | F30: 46078 | G30: 46085 | H30: D09 | I30: DR153 | J30: DG22 | K30: Emergency | L30: Doctor Referral | M30: 57700 | N30: 8650 | O30: 7350 | P30: 17500 | Q30: 93200 | R30: IP01 | S30: Approved | T30: 42240 | U30: 3 | V30: Yes | W30: 46095 | X30: Yes | Y30: No | Z30: Recovered | AA30: =VLOOKUP(H30,Departments!$A:$B,2,0) -> Pulmonology | AB30: =VLOOKUP(J30,Diagnosis_Guide!$A:$B,2,0) -> Pneumonia | AC30: =VLOOKUP(J30,Diagnosis_Guide!$A:$C,3,0) -> Respiratory | AD30: =VLOOKUP(R30,Insurance_Plans!$A:$C,3,0) -> Public | AE30: =IF(Q30="","",Q30*0.05) -> 4660 | AF30: =IF(Q30="","",Q30+AE30) -> 97860 | AG30: =IF(U30="","Not Available",IF(U30>=4,"High",IF(U30=3,"Medium","Low"))) -> Medium
A31: V10030 | B31: P2571 | C31: 46106 | D31: 15:00 | E31: Attended | F31: 46107 | G31: 46112 | H31: D08 | I31: DR143 | J31: DG21 | K31: Inpatient | L31: Scheduled Appointment | M31: 57600 | N31: 9550 | O31: 7400 | P31: 12500 | Q31: 87850 | R31: IP06 | S31: Pending | T31: 26760 | U31: 3 | V31: No | X31: Not Required | Y31: Yes | Z31: Recovered | AA31: =VLOOKUP(H31,Departments!$A:$B,2,0) -> Nephrology | AB31: =VLOOKUP(J31,Diagnosis_Guide!$A:$B,2,0) -> Dialysis Complication | AC31: =VLOOKUP(J31,Diagnosis_Guide!$A:$C,3,0) -> Renal | AD31: =VLOOKUP(R31,Insurance_Plans!$A:$C,3,0) -> Public | AE31: =IF(Q31="","",Q31*0.05) -> 4392.5 | AF31: =IF(Q31="","",Q31+AE31) -> 92242.5 | AG31: =IF(U31="","Not Available",IF(U31>=4,"High",IF(U31=3,"Medium","Low"))) -> Medium
A32: V10031 | B32: P2405 | C32: 46049 | D32: 10:00 | E32: Attended | F32: 46050 | G32: 46056 | H32: D06 | I32: DR135 | J32: DG13 | K32: Surgery | L32: Scheduled Appointment | M32: 58300 | N32: 8800 | O32: 10900 | P32: 21000 | Q32: 100500 | R32: IP05 | S32: Not Applicable | T32: 100500 | U32: 5 | V32: No | X32: Not Required | Y32: No | Z32: Against Medical Advice | AA32: =VLOOKUP(H32,Departments!$A:$B,2,0) -> Surgery | AB32: =VLOOKUP(J32,Diagnosis_Guide!$A:$B,2,0) -> Appendicitis Surgery | AC32: =VLOOKUP(J32,Diagnosis_Guide!$A:$C,3,0) -> Surgical | AD32: =VLOOKUP(R32,Insurance_Plans!$A:$C,3,0) -> Self-Pay | AE32: =IF(Q32="","",Q32*0.05) -> 5025 | AF32: =IF(Q32="","",Q32+AE32) -> 105525 | AG32: =IF(U32="","Not Available",IF(U32>=4,"High",IF(U32=3,"Medium","Low"))) -> High
A33: V10032 | B33: P2126 | C33: 46082 | D33: 10:00 | E33: Attended | F33: 46082 | G33: 46083 | H33: D05 | I33: DR128 | J33: DG11 | K33: Outpatient | L33: Doctor Referral | M33: 23400 | N33: 3450 | O33: 2900 | P33: 6000 | Q33: 36750 | R33: IP04 | S33: Approved | T33: 10090 | U33: 5 | V33: No | X33: Not Required | Y33: No | Z33: Recovered | AA33: =VLOOKUP(H33,Departments!$A:$B,2,0) -> General Medicine | AB33: =VLOOKUP(J33,Diagnosis_Guide!$A:$B,2,0) -> Diabetes Complication | AC33: =VLOOKUP(J33,Diagnosis_Guide!$A:$C,3,0) -> Endocrine/General | AD33: =VLOOKUP(R33,Insurance_Plans!$A:$C,3,0) -> Employer | AE33: =IF(Q33="","",Q33*0.05) -> 1837.5 | AF33: =IF(Q33="","",Q33+AE33) -> 38587.5 | AG33: =IF(U33="","Not Available",IF(U33>=4,"High",IF(U33=3,"Medium","Low"))) -> High
A34: V10033 | B34: P2352 | C34: 46162 | D34: 08:00 | E34: Rescheduled | H34: D09 | I34: DR153 | J34: DG23 | K34: Emergency | L34: Doctor Referral | R34: IP04 | S34: Not Applicable | V34: No | X34: Not Required | Z34: Not Treated | AA34: =VLOOKUP(H34,Departments!$A:$B,2,0) -> Pulmonology | AB34: =VLOOKUP(J34,Diagnosis_Guide!$A:$B,2,0) -> COPD Exacerbation | AC34: =VLOOKUP(J34,Diagnosis_Guide!$A:$C,3,0) -> Respiratory | AD34: =VLOOKUP(R34,Insurance_Plans!$A:$C,3,0) -> Employer | AE34: =IF(Q34="","",Q34*0.05) | AF34: =IF(Q34="","",Q34+AE34) | AG34: =IF(U34="","Not Available",IF(U34>=4,"High",IF(U34=3,"Medium","Low"))) -> Not Available
A35: V10034 | B35: P2323 | C35: 46140 | D35: 08:00 | E35: Attended | F35: 46140 | G35: 46142 | H35: D10 | I35: DR158 | J35: DG26 | K35: Inpatient | L35: Scheduled Appointment | M35: 47900 | N35: 6150 | O35: 5600 | P35: 9000 | Q35: 70150 | R35: IP04 | S35: Approved | T35: 18440 | U35: 4 | V35: No | X35: Not Required | Y35: No | Z35: Recovered | AA35: =VLOOKUP(H35,Departments!$A:$B,2,0) -> Obstetrics | AB35: =VLOOKUP(J35,Diagnosis_Guide!$A:$B,2,0) -> Delivery Care | AC35: =VLOOKUP(J35,Diagnosis_Guide!$A:$C,3,0) -> Maternal Health | AD35: =VLOOKUP(R35,Insurance_Plans!$A:$C,3,0) -> Employer | AE35: =IF(Q35="","",Q35*0.05) -> 3507.5 | AF35: =IF(Q35="","",Q35+AE35) -> 73657.5 | AG35: =IF(U35="","Not Available",IF(U35>=4,"High",IF(U35=3,"Medium","Low"))) -> High
A36: V10035 | B36: P2362 | C36: 46105 | D36: 08:00 | E36: Attended | F36: 46105 | G36: 46105 | H36: D09 | I36: DR151 | J36: DG23 | K36: Outpatient | L36: Emergency Walk-in | M36: 49400 | N36: 6050 | O36: 12300 | P36: 0 | Q36: 68950 | R36: IP03 | S36: Approved | T36: 11540 | U36: 4 | V36: Yes | W36: 46115 | X36: Yes | Y36: No | Z36: Recovered | AA36: =VLOOKUP(H36,Departments!$A:$B,2,0) -> Pulmonology | AB36: =VLOOKUP(J36,Diagnosis_Guide!$A:$B,2,0) -> COPD Exacerbation | AC36: =VLOOKUP(J36,Diagnosis_Guide!$A:$C,3,0) -> Respiratory | AD36: =VLOOKUP(R36,Insurance_Plans!$A:$C,3,0) -> Private | AE36: =IF(Q36="","",Q36*0.05) -> 3447.5 | AF36: =IF(Q36="","",Q36+AE36) -> 72397.5 | AG36: =IF(U36="","Not Available",IF(U36>=4,"High",IF(U36=3,"Medium","Low"))) -> High
A37: V10036 | B37: P2433 | C37: 46091 | D37: 08:45 | E37: Attended | F37: 46092 | G37: 46096 | H37: D07 | I37: DR140 | J37: DG18 | K37: Surgery | L37: Emergency Walk-in | M37: 41800 | N37: 4200 | O37: 7300 | P37: 14000 | Q37: 68300 | R37: IP01 | S37: Approved | T37: 31030 | U37: 4 | V37: Yes | W37: 46113 | X37: No | Y37: No | Z37: Recovered | AA37: =VLOOKUP(H37,Departments!$A:$B,2,0) -> Pediatrics | AB37: =VLOOKUP(J37,Diagnosis_Guide!$A:$B,2,0) -> Neonatal Observation | AC37: =VLOOKUP(J37,Diagnosis_Guide!$A:$C,3,0) -> Pediatric | AD37: =VLOOKUP(R37,Insurance_Plans!$A:$C,3,0) -> Public | AE37: =IF(Q37="","",Q37*0.05) -> 3415 | AF37: =IF(Q37="","",Q37+AE37) -> 71715 | AG37: =IF(U37="","Not Available",IF(U37>=4,"High",IF(U37=3,"Medium","Low"))) -> High
A38: V10037 | B38: P2095 | C38: 46047 | D38: 17:30 | E38: Attended | F38: 46048 | G38: 46051 | H38: D10 | I38: DR159 | J38: DG25 | K38: Inpatient | L38: Emergency Walk-in | M38: 20400 | N38: 3250 | O38: 4050 | P38: 10500 | Q38: 40000 | R38: IP03 | S38: Approved | T38: 7200 | U38: 5 | V38: No | X38: Not Required | Y38: No | Z38: Improved | AA38: =VLOOKUP(H38,Departments!$A:$B,2,0) -> Obstetrics | AB38: =VLOOKUP(J38,Diagnosis_Guide!$A:$B,2,0) -> Antenatal Complication | AC38: =VLOOKUP(J38,Diagnosis_Guide!$A:$C,3,0) -> Maternal Health | AD38: =VLOOKUP(R38,Insurance_Plans!$A:$C,3,0) -> Private | AE38: =IF(Q38="","",Q38*0.05) -> 2000 | AF38: =IF(Q38="","",Q38+AE38) -> 42000 | AG38: =IF(U38="","Not Available",IF(U38>=4,"High",IF(U38=3,"Medium","Low"))) -> High
A39: V10038 | B39: P2020 | C39: 46070 | D39: 17:45 | E39: Attended | F39: 46071 | G39: 46076 | H39: D08 | I39: DR147 | J39: DG20 | K39: Surgery | L39: Scheduled Appointment | M39: 90800 | N39: 15500 | O39: 21800 | P39: 12500 | Q39: 142400 | R39: IP03 | S39: Approved | T39: 22560 | U39: 3 | V39: Yes | W39: 46085 | X39: No | Y39: No | Z39: Stable | AA39: =VLOOKUP(H39,Departments!$A:$B,2,0) -> Nephrology | AB39: =VLOOKUP(J39,Diagnosis_Guide!$A:$B,2,0) -> Chronic Kidney Disease | AC39: =VLOOKUP(J39,Diagnosis_Guide!$A:$C,3,0) -> Renal | AD39: =VLOOKUP(R39,Insurance_Plans!$A:$C,3,0) -> Private | AE39: =IF(Q39="","",Q39*0.05) -> 7120 | AF39: =IF(Q39="","",Q39+AE39) -> 149520 | AG39: =IF(U39="","Not Available",IF(U39>=4,"High",IF(U39=3,"Medium","Low"))) -> Medium
A40: V10039 | B40: P2274 | C40: 46064 | D40: 12:15 | E40: Attended | F40: 46064 | G40: 46064 | H40: D10 | I40: DR160 | J40: DG27 | K40: Outpatient | L40: Doctor Referral | M40: 83200 | N40: 14900 | O40: 13600 | P40: 0 | Q40: 112700 | R40: IP06 | S40: Approved | T40: 34210 | U40: 5 | V40: Yes | W40: 46071 | X40: Yes | Y40: No | Z40: Stable | AA40: =VLOOKUP(H40,Departments!$A:$B,2,0) -> Obstetrics | AB40: =VLOOKUP(J40,Diagnosis_Guide!$A:$B,2,0) -> Emergency C-Section | AC40: =VLOOKUP(J40,Diagnosis_Guide!$A:$C,3,0) -> Maternal Health | AD40: =VLOOKUP(R40,Insurance_Plans!$A:$C,3,0) -> Public | AE40: =IF(Q40="","",Q40*0.05) -> 5635 | AF40: =IF(Q40="","",Q40+AE40) -> 118335 | AG40: =IF(U40="","Not Available",IF(U40>=4,"High",IF(U40=3,"Medium","Low"))) -> High
A41: V10040 | B41: P2086 | C41: 46039 | D41: 14:30 | E41: Attended | F41: 46039 | G41: 46045 | H41: D03 | I41: DR115 | J41: DG04 | K41: Emergency | L41: Emergency Walk-in | M41: 64300 | N41: 9400 | O41: 12050 | P41: 36000 | Q41: 123750 | R41: IP02 | S41: Pending | T41: 44010 | U41: 4 | V41: Yes | W41: 46053 | X41: No | Y41: No | Z41: Stable | AA41: =VLOOKUP(H41,Departments!$A:$B,2,0) -> Neurology | AB41: =VLOOKUP(J41,Diagnosis_Guide!$A:$B,2,0) -> Stroke Assessment | AC41: =VLOOKUP(J41,Diagnosis_Guide!$A:$C,3,0) -> Neurological | AD41: =VLOOKUP(R41,Insurance_Plans!$A:$C,3,0) -> Private | AE41: =IF(Q41="","",Q41*0.05) -> 6187.5 | AF41: =IF(Q41="","",Q41+AE41) -> 129937.5 | AG41: =IF(U41="","Not Available",IF(U41>=4,"High",IF(U41=3,"Medium","Low"))) -> High
A42: V10041 | B42: P2110 | C42: 46135 | D42: 14:30 | E42: Missed | H42: D03 | I42: DR115 | J42: DG05 | K42: Emergency | L42: Doctor Referral | R42: IP05 | S42: Not Applicable | V42: No | X42: Not Required | Z42: Not Treated | AA42: =VLOOKUP(H42,Departments!$A:$B,2,0) -> Neurology | AB42: =VLOOKUP(J42,Diagnosis_Guide!$A:$B,2,0) -> Migraine Complication | AC42: =VLOOKUP(J42,Diagnosis_Guide!$A:$C,3,0) -> Neurological | AD42: =VLOOKUP(R42,Insurance_Plans!$A:$C,3,0) -> Self-Pay | AE42: =IF(Q42="","",Q42*0.05) | AF42: =IF(Q42="","",Q42+AE42) | AG42: =IF(U42="","Not Available",IF(U42>=4,"High",IF(U42=3,"Medium","Low"))) -> Not Available
A43: V10042 | B43: P2434 | C43: 46094 | D43: 10:30 | E43: Attended | F43: 46094 | G43: 46095 | H43: D07 | I43: DR138 | J43: DG17 | K43: Outpatient | L43: Emergency Walk-in | N43: 1050 | O43: 1200 | P43: 3000 | Q43: 13750 | R43: IP02 | S43: Approved | T43: 5510 | U43: 3 | V43: No | X43: Not Required | Y43: No | Z43: Recovered | AA43: =VLOOKUP(H43,Departments!$A:$B,2,0) -> Pediatrics | AB43: =VLOOKUP(J43,Diagnosis_Guide!$A:$B,2,0) -> Child Fever | AC43: =VLOOKUP(J43,Diagnosis_Guide!$A:$C,3,0) -> Pediatric | AD43: =VLOOKUP(R43,Insurance_Plans!$A:$C,3,0) -> Private | AE43: =IF(Q43="","",Q43*0.05) -> 687.5 | AF43: =IF(Q43="","",Q43+AE43) -> 14437.5 | AG43: =IF(U43="","Not Available",IF(U43>=4,"High",IF(U43=3,"Medium","Low"))) -> Medium
A44: V10043 | B44: P2262 | C44: 46099 | D44: 11:15 | E44: Cancelled | H44: D05 | I44: DR126 | J44: DG10 | K44: Emergency | L44: Scheduled Appointment | R44: IP04 | S44: Not Applicable | V44: No | X44: Not Required | Z44: Not Treated | AA44: =VLOOKUP(H44,Departments!$A:$B,2,0) -> General Medicine | AB44: =VLOOKUP(J44,Diagnosis_Guide!$A:$B,2,0) -> Fever Investigation | AC44: =VLOOKUP(J44,Diagnosis_Guide!$A:$C,3,0) -> Infectious/General | AD44: =VLOOKUP(R44,Insurance_Plans!$A:$C,3,0) -> Employer | AE44: =IF(Q44="","",Q44*0.05) | AF44: =IF(Q44="","",Q44+AE44) | AG44: =IF(U44="","Not Available",IF(U44>=4,"High",IF(U44=3,"Medium","Low"))) -> Not Available
A45: V10044 | B45: P2035 | C45: 46148 | D45: 15:45 | E45: Cancelled | H45: D05 | I45: DR125 | J45: DG10 | K45: Inpatient | L45: Scheduled Appointment | R45: IP01 | S45: Not Applicable | V45: No | X45: Not Required | Z45: Not Treated | AA45: =VLOOKUP(H45,Departments!$A:$B,2,0) -> General Medicine | AB45: =VLOOKUP(J45,Diagnosis_Guide!$A:$B,2,0) -> Fever Investigation | AC45: =VLOOKUP(J45,Diagnosis_Guide!$A:$C,3,0) -> Infectious/General | AD45: =VLOOKUP(R45,Insurance_Plans!$A:$C,3,0) -> Public | AE45: =IF(Q45="","",Q45*0.05) | AF45: =IF(Q45="","",Q45+AE45) | AG45: =IF(U45="","Not Available",IF(U45>=4,"High",IF(U45=3,"Medium","Low"))) -> Not Available
A46: V10045 | B46: P2165 | C46: 46039 | D46: 13:45 | E46: Attended | F46: 46040 | G46: 46044 | H46: D08 | I46: DR147 | J46: DG20 | K46: Emergency | L46: Scheduled Appointment | M46: 57000 | N46: 7100 | O46: 11200 | P46: 10000 | Q46: 87100 | R46: IP03 | S46: Approved | T46: 14270 | U46: 5 | V46: Yes | W46: 46052 | X46: Yes | Y46: No | Z46: Improved | AA46: =VLOOKUP(H46,Departments!$A:$B,2,0) -> Nephrology | AB46: =VLOOKUP(J46,Diagnosis_Guide!$A:$B,2,0) -> Chronic Kidney Disease | AC46: =VLOOKUP(J46,Diagnosis_Guide!$A:$C,3,0) -> Renal | AD46: =VLOOKUP(R46,Insurance_Plans!$A:$C,3,0) -> Private | AE46: =IF(Q46="","",Q46*0.05) -> 4355 | AF46: =IF(Q46="","",Q46+AE46) -> 91455 | AG46: =IF(U46="","Not Available",IF(U46>=4,"High",IF(U46=3,"Medium","Low"))) -> High
A47: V10046 | B47: P2137 | C47: 46106 | D47: 12:15 | E47: Attended | F47: 46107 | G47: 46108 | H47: D04 | I47: DR124 | J47: DG09 | K47: Outpatient | L47: Emergency Walk-in | M47: 66800 | N47: 11700 | O47: 15950 | P47: 6000 | Q47: 102250 | R47: IP04 | S47: Pending | T47: 26460 | U47: 4 | V47: Yes | W47: 46126 | X47: No | Y47: Yes | Z47: Recovered | AA47: =VLOOKUP(H47,Departments!$A:$B,2,0) -> Orthopedics | AB47: =VLOOKUP(J47,Diagnosis_Guide!$A:$B,2,0) -> Spinal Injury | AC47: =VLOOKUP(J47,Diagnosis_Guide!$A:$C,3,0) -> Musculoskeletal | AD47: =VLOOKUP(R47,Insurance_Plans!$A:$C,3,0) -> Employer | AE47: =IF(Q47="","",Q47*0.05) -> 5112.5 | AF47: =IF(Q47="","",Q47+AE47) -> 107362.5 | AG47: =IF(U47="","Not Available",IF(U47>=4,"High",IF(U47=3,"Medium","Low"))) -> High
A48: V10047 | B48: P2121 | C48: 46134 | D48: 15:45 | E48: Attended | F48: 46134 | G48: 46136 | H48: D02 | I48: DR111 | J48: DG01 | K48: Emergency | L48: Doctor Referral | M48: 16500 | N48: 2750 | O48: 3150 | P48: 7000 | Q48: 31400 | R48: IP05 | S48: Not Applicable | T48: 31400 | U48: 5 | V48: Yes | W48: 46145 | X48: Yes | Y48: No | Z48: Recovered | AA48: =VLOOKUP(H48,Departments!$A:$B,2,0) -> Cardiology | AB48: =VLOOKUP(J48,Diagnosis_Guide!$A:$B,2,0) -> Chest Pain | AC48: =VLOOKUP(J48,Diagnosis_Guide!$A:$C,3,0) -> Cardiovascular | AD48: =VLOOKUP(R48,Insurance_Plans!$A:$C,3,0) -> Self-Pay | AE48: =IF(Q48="","",Q48*0.05) -> 1570 | AF48: =IF(Q48="","",Q48+AE48) -> 32970 | AG48: =IF(U48="","Not Available",IF(U48>=4,"High",IF(U48=3,"Medium","Low"))) -> High
A49: V10048 | B49: P2470 | C49: 46057 | D49: 13:45 | E49: Attended | F49: 46057 | G49: 46068 | H49: D03 | I49: DR116 | J49: DG04 | K49: Emergency | L49: Scheduled Appointment | M49: 61800 | N49: 7000 | O49: 8350 | P49: 38500 | Q49: 117450 | R49: IP07 | S49: Pending | T49: 64800 | V49: No | X49: Not Required | Y49: No | Z49: Improved | AA49: =VLOOKUP(H49,Departments!$A:$B,2,0) -> Neurology | AB49: =VLOOKUP(J49,Diagnosis_Guide!$A:$B,2,0) -> Stroke Assessment | AC49: =VLOOKUP(J49,Diagnosis_Guide!$A:$C,3,0) -> Neurological | AD49: =VLOOKUP(R49,Insurance_Plans!$A:$C,3,0) -> Community | AE49: =IF(Q49="","",Q49*0.05) -> 5872.5 | AF49: =IF(Q49="","",Q49+AE49) -> 123322.5 | AG49: =IF(U49="","Not Available",IF(U49>=4,"High",IF(U49=3,"Medium","Low"))) -> Not Available
A50: V10049 | B50: P2136 | C50: 46033 | D50: 17:15 | E50: Attended | F50: 46033 | G50: 46033 | H50: D01 | I50: DR105 | J50: DG30 | K50: Outpatient | L50: Scheduled Appointment | M50: 5900 | N50: 650 | O50: 1450 | P50: 0 | Q50: 9000 | R50: IP03 | S50: Rejected | T50: 2550 | U50: 4 | V50: Yes | W50: 46045 | X50: No | Y50: No | Z50: Stable | AA50: =VLOOKUP(H50,Departments!$A:$B,2,0) -> Emergency | AB50: =VLOOKUP(J50,Diagnosis_Guide!$A:$B,2,0) -> Food Poisoning | AC50: =VLOOKUP(J50,Diagnosis_Guide!$A:$C,3,0) -> Emergency | AD50: =VLOOKUP(R50,Insurance_Plans!$A:$C,3,0) -> Private | AE50: =IF(Q50="","",Q50*0.05) -> 450 | AF50: =IF(Q50="","",Q50+AE50) -> 9450 | AG50: =IF(U50="","Not Available",IF(U50>=4,"High",IF(U50=3,"Medium","Low"))) -> High
A51: V10050 | B51: P2324 | C51: 46061 | D51: 16:45 | E51: Attended | F51: 46061 | G51: 46061 | H51: D09 | I51: DR152 | J51: DG22 | K51: Outpatient | L51: Doctor Referral | M51: 50800 | N51: 4650 | O51: 11900 | P51: 0 | Q51: 69850 | R51: IP03 | S51: Approved | T51: 11680 | U51: 3 | V51: No | X51: Not Required | Y51: No | Z51: Stable | AA51: =VLOOKUP(H51,Departments!$A:$B,2,0) -> Pulmonology | AB51: =VLOOKUP(J51,Diagnosis_Guide!$A:$B,2,0) -> Pneumonia | AC51: =VLOOKUP(J51,Diagnosis_Guide!$A:$C,3,0) -> Respiratory | AD51: =VLOOKUP(R51,Insurance_Plans!$A:$C,3,0) -> Private | AE51: =IF(Q51="","",Q51*0.05) -> 3492.5 | AF51: =IF(Q51="","",Q51+AE51) -> 73342.5 | AG51: =IF(U51="","Not Available",IF(U51>=4,"High",IF(U51=3,"Medium","Low"))) -> Medium
A52: V10051 | B52: P2185 | C52: 46153 | D52: 12:15 | E52: Attended | F52: 46153 | G52: 46156 | H52: D10 | I52: DR160 | J52: DG26 | K52: Surgery | L52: Emergency Walk-in | M52: 43100 | N52: 6350 | O52: 10050 | P52: 7500 | Q52: 68000 | R52: IP02 | S52: Rejected | T52: 24500 | U52: 5 | V52: Yes | W52: 46168 | X52: Yes | Y52: No | Z52: Recovered | AA52: =VLOOKUP(H52,Departments!$A:$B,2,0) -> Obstetrics | AB52: =VLOOKUP(J52,Diagnosis_Guide!$A:$B,2,0) -> Delivery Care | AC52: =VLOOKUP(J52,Diagnosis_Guide!$A:$C,3,0) -> Maternal Health | AD52: =VLOOKUP(R52,Insurance_Plans!$A:$C,3,0) -> Private | AE52: =IF(Q52="","",Q52*0.05) -> 3400 | AF52: =IF(Q52="","",Q52+AE52) -> 71400 | AG52: =IF(U52="","Not Available",IF(U52>=4,"High",IF(U52=3,"Medium","Low"))) -> High
A53: V10052 | B53: P2276 | C53: 46107 | D53: 08:45 | E53: Attended | F53: 46107 | G53: 46113 | H53: D08 | I53: DR143 | J53: DG21 | K53: Emergency | L53: Scheduled Appointment | M53: 58100 | N53: 6300 | O53: 12750 | P53: 15000 | Q53: 92950 | R53: IP04 | S53: Approved | T53: 24140 | U53: 4 | V53: Yes | W53: 46124 | X53: Yes | Y53: No | Z53: Stable | AA53: =VLOOKUP(H53,Departments!$A:$B,2,0) -> Nephrology | AB53: =VLOOKUP(J53,Diagnosis_Guide!$A:$B,2,0) -> Dialysis Complication | AC53: =VLOOKUP(J53,Diagnosis_Guide!$A:$C,3,0) -> Renal | AD53: =VLOOKUP(R53,Insurance_Plans!$A:$C,3,0) -> Employer | AE53: =IF(Q53="","",Q53*0.05) -> 4647.5 | AF53: =IF(Q53="","",Q53+AE53) -> 97597.5 | AG53: =IF(U53="","Not Available",IF(U53>=4,"High",IF(U53=3,"Medium","Low"))) -> High
A54: V10053 | B54: P2158 | C54: 46133 | D54: 12:15 | E54: Attended | F54: 46133 | G54: 46133 | H54: D04 | I54: DR122 | J54: DG07 | K54: Outpatient | L54: Emergency Walk-in | M54: 41000 | N54: 5000 | O54: 8750 | P54: 0 | Q54: 57250 | R54: IP05 | S54: Not Applicable | T54: 57250 | U54: 5 | V54: No | X54: Not Required | Y54: No | Z54: Improved | AA54: =VLOOKUP(H54,Departments!$A:$B,2,0) -> Orthopedics | AB54: =VLOOKUP(J54,Diagnosis_Guide!$A:$B,2,0) -> Fracture Repair | AC54: =VLOOKUP(J54,Diagnosis_Guide!$A:$C,3,0) -> Musculoskeletal | AD54: =VLOOKUP(R54,Insurance_Plans!$A:$C,3,0) -> Self-Pay | AE54: =IF(Q54="","",Q54*0.05) -> 2862.5 | AF54: =IF(Q54="","",Q54+AE54) -> 60112.5 | AG54: =IF(U54="","Not Available",IF(U54>=4,"High",IF(U54=3,"Medium","Low"))) -> High
A55: V10054 | B55: P2159 | C55: 46157 | D55: 09:30 | E55: Attended | F55: 46157 | G55: 46161 | H55: D01 | I55: DR105 | J55: DG29 | K55: Inpatient | L55: Emergency Walk-in | M55: 38700 | N55: 4050 | O55: 6350 | P55: 24000 | Q55: 74100 | R55: IP01 | S55: Approved | T55: 33640 | U55: 4 | V55: Yes | W55: 46169 | X55: Yes | Y55: No | Z55: Improved | AA55: =VLOOKUP(H55,Departments!$A:$B,2,0) -> Emergency | AB55: =VLOOKUP(J55,Diagnosis_Guide!$A:$B,2,0) -> Accident Injury | AC55: =VLOOKUP(J55,Diagnosis_Guide!$A:$C,3,0) -> Emergency | AD55: =VLOOKUP(R55,Insurance_Plans!$A:$C,3,0) -> Public | AE55: =IF(Q55="","",Q55*0.05) -> 3705 | AF55: =IF(Q55="","",Q55+AE55) -> 77805 | AG55: =IF(U55="","Not Available",IF(U55>=4,"High",IF(U55=3,"Medium","Low"))) -> High
A56: V10055 | B56: P2516 | C56: 46141 | D56: 10:15 | E56: Missed | H56: D02 | I56: DR112 | J56: DG01 | K56: Emergency | L56: Emergency Walk-in | R56: IP05 | S56: Not Applicable | V56: No | X56: Not Required | Z56: Not Treated | AA56: =VLOOKUP(H56,Departments!$A:$B,2,0) -> Cardiology | AB56: =VLOOKUP(J56,Diagnosis_Guide!$A:$B,2,0) -> Chest Pain | AC56: =VLOOKUP(J56,Diagnosis_Guide!$A:$C,3,0) -> Cardiovascular | AD56: =VLOOKUP(R56,Insurance_Plans!$A:$C,3,0) -> Self-Pay | AE56: =IF(Q56="","",Q56*0.05) | AF56: =IF(Q56="","",Q56+AE56) | AG56: =IF(U56="","Not Available",IF(U56>=4,"High",IF(U56=3,"Medium","Low"))) -> Not Available
A57: V10056 | B57: P2466 | C57: 46090 | D57: 13:15 | E57: Attended | F57: 46090 | G57: 46090 | H57: D10 | I57: DR158 | J57: DG26 | K57: Outpatient | L57: Transfer from Clinic | M57: 28300 | N57: 2600 | O57: 3550 | P57: 0 | Q57: 35950 | R57: IP03 | S57: Approved | T57: 6590 | U57: 5 | V57: No | X57: Not Required | Y57: No | Z57: Recovered | AA57: =VLOOKUP(H57,Departments!$A:$B,2,0) -> Obstetrics | AB57: =VLOOKUP(J57,Diagnosis_Guide!$A:$B,2,0) -> Delivery Care | AC57: =VLOOKUP(J57,Diagnosis_Guide!$A:$C,3,0) -> Maternal Health | AD57: =VLOOKUP(R57,Insurance_Plans!$A:$C,3,0) -> Private | AE57: =IF(Q57="","",Q57*0.05) -> 1797.5 | AF57: =IF(Q57="","",Q57+AE57) -> 37747.5 | AG57: =IF(U57="","Not Available",IF(U57>=4,"High",IF(U57=3,"Medium","Low"))) -> High
A58: V10057 | B58: P2405 | C58: 46055 | D58: 10:00 | E58: Attended | F58: 46055 | G58: 46060 | H58: D10 | I58: DR155 | J58: DG27 | K58: Emergency | L58: Scheduled Appointment | M58: 71300 | N58: 10350 | O58: 14100 | P58: 22500 | Q58: 119450 | R58: IP05 | S58: Not Applicable | T58: 119450 | U58: 4 | V58: No | X58: Not Required | Y58: Yes | Z58: Improved | AA58: =VLOOKUP(H58,Departments!$A:$B,2,0) -> Obstetrics | AB58: =VLOOKUP(J58,Diagnosis_Guide!$A:$B,2,0) -> Emergency C-Section | AC58: =VLOOKUP(J58,Diagnosis_Guide!$A:$C,3,0) -> Maternal Health | AD58: =VLOOKUP(R58,Insurance_Plans!$A:$C,3,0) -> Self-Pay | AE58: =IF(Q58="","",Q58*0.05) -> 5972.5 | AF58: =IF(Q58="","",Q58+AE58) -> 125422.5 | AG58: =IF(U58="","Not Available",IF(U58>=4,"High",IF(U58=3,"Medium","Low"))) -> High
A59: V10058 | B59: P2456 | C59: 46028 | D59: 15:15 | E59: Attended | F59: 46028 | G59: 46034 | H59: D01 | I59: DR104 | J59: DG29 | K59: Inpatient | L59: Doctor Referral | M59: 52900 | N59: 6850 | O59: 9900 | P59: 36000 | Q59: 108150 | R59: IP07 | S59: Approved | T59: 59680 | U59: 3 | V59: Yes | W59: 46049 | X59: Yes | Y59: No | Z59: Recovered | AA59: =VLOOKUP(H59,Departments!$A:$B,2,0) -> Emergency | AB59: =VLOOKUP(J59,Diagnosis_Guide!$A:$B,2,0) -> Accident Injury | AC59: =VLOOKUP(J59,Diagnosis_Guide!$A:$C,3,0) -> Emergency | AD59: =VLOOKUP(R59,Insurance_Plans!$A:$C,3,0) -> Community | AE59: =IF(Q59="","",Q59*0.05) -> 5407.5 | AF59: =IF(Q59="","",Q59+AE59) -> 113557.5 | AG59: =IF(U59="","Not Available",IF(U59>=4,"High",IF(U59=3,"Medium","Low"))) -> Medium
A60: V10059 | B60: P2275 | C60: 46144 | D60: 09:45 | E60: Attended | F60: 46144 | G60: 46149 | H60: D01 | I60: DR104 | J60: DG28 | K60: Emergency | L60: Emergency Walk-in | M60: 40200 | N60: 5000 | O60: 7100 | P60: 30000 | Q60: 84800 | R60: IP06 | S60: Approved | T60: 25840 | U60: 2 | V60: Yes | W60: 46169 | X60: No | Y60: No | Z60: Recovered | AA60: =VLOOKUP(H60,Departments!$A:$B,2,0) -> Emergency | AB60: =VLOOKUP(J60,Diagnosis_Guide!$A:$B,2,0) -> Trauma Observation | AC60: =VLOOKUP(J60,Diagnosis_Guide!$A:$C,3,0) -> Emergency | AD60: =VLOOKUP(R60,Insurance_Plans!$A:$C,3,0) -> Public | AE60: =IF(Q60="","",Q60*0.05) -> 4240 | AF60: =IF(Q60="","",Q60+AE60) -> 89040 | AG60: =IF(U60="","Not Available",IF(U60>=4,"High",IF(U60=3,"Medium","Low"))) -> Low
A61: V10060 | B61: P2369 | C61: 46076 | D61: 12:00 | E61: Attended | F61: 46077 | G61: 46077 | H61: D10 | I61: DR156 | J61: DG27 | K61: Outpatient | L61: Doctor Referral | M61: 71300 | N61: 6050 | O61: 7300 | P61: 0 | Q61: 87150 | R61: IP06 | S61: Approved | T61: 26550 | U61: 3 | V61: Yes | W61: 46097 | X61: No | Y61: No | Z61: Recovered | AA61: =VLOOKUP(H61,Departments!$A:$B,2,0) -> Obstetrics | AB61: =VLOOKUP(J61,Diagnosis_Guide!$A:$B,2,0) -> Emergency C-Section | AC61: =VLOOKUP(J61,Diagnosis_Guide!$A:$C,3,0) -> Maternal Health | AD61: =VLOOKUP(R61,Insurance_Plans!$A:$C,3,0) -> Public | AE61: =IF(Q61="","",Q61*0.05) -> 4357.5 | AF61: =IF(Q61="","",Q61+AE61) -> 91507.5 | AG61: =IF(U61="","Not Available",IF(U61>=4,"High",IF(U61=3,"Medium","Low"))) -> Medium
A62: V10061 | B62: P2349 | C62: 46165 | D62: 12:15 | E62: No Show | H62: D10 | I62: DR155 | J62: DG26 | K62: Inpatient | L62: Doctor Referral | R62: IP01 | S62: Not Applicable | V62: No | X62: Not Required | Z62: Not Treated | AA62: =VLOOKUP(H62,Departments!$A:$B,2,0) -> Obstetrics | AB62: =VLOOKUP(J62,Diagnosis_Guide!$A:$B,2,0) -> Delivery Care | AC62: =VLOOKUP(J62,Diagnosis_Guide!$A:$C,3,0) -> Maternal Health | AD62: =VLOOKUP(R62,Insurance_Plans!$A:$C,3,0) -> Public | AE62: =IF(Q62="","",Q62*0.05) | AF62: =IF(Q62="","",Q62+AE62) | AG62: =IF(U62="","Not Available",IF(U62>=4,"High",IF(U62=3,"Medium","Low"))) -> Not Available
A63: V10062 | B63: P2449 | C63: 46050 | D63: 17:00 | E63: No-show | H63: D10 | I63: DR155 | J63: DG26 | K63: Outpatient | L63: Doctor Referral | R63: IP02 | S63: Not Applicable | V63: No | X63: Not Required | Z63: Not Treated | AA63: =VLOOKUP(H63,Departments!$A:$B,2,0) -> Obstetrics | AB63: =VLOOKUP(J63,Diagnosis_Guide!$A:$B,2,0) -> Delivery Care | AC63: =VLOOKUP(J63,Diagnosis_Guide!$A:$C,3,0) -> Maternal Health | AD63: =VLOOKUP(R63,Insurance_Plans!$A:$C,3,0) -> Private | AE63: =IF(Q63="","",Q63*0.05) | AF63: =IF(Q63="","",Q63+AE63) | AG63: =IF(U63="","Not Available",IF(U63>=4,"High",IF(U63=3,"Medium","Low"))) -> Not Available
A64: V10063 | B64: P2371 | C64: 46136 | D64: 16:45 | E64: Attended | F64: 46136 | G64: 46136 | H64: D03 | I64: DR115 | J64: DG04 | K64: Outpatient | L64: Scheduled Appointment | M64: 59900 | N64: 10600 | O64: 12900 | P64: 0 | Q64: 85400 | R64: IP01 | S64: Pending | T64: 38730 | U64: 4 | V64: Yes | W64: 46147 | X64: Yes | Y64: Yes | Z64: Recovered | AA64: =VLOOKUP(H64,Departments!$A:$B,2,0) -> Neurology | AB64: =VLOOKUP(J64,Diagnosis_Guide!$A:$B,2,0) -> Stroke Assessment | AC64: =VLOOKUP(J64,Diagnosis_Guide!$A:$C,3,0) -> Neurological | AD64: =VLOOKUP(R64,Insurance_Plans!$A:$C,3,0) -> Public | AE64: =IF(Q64="","",Q64*0.05) -> 4270 | AF64: =IF(Q64="","",Q64+AE64) -> 89670 | AG64: =IF(U64="","Not Available",IF(U64>=4,"High",IF(U64=3,"Medium","Low"))) -> High
A65: V10064 | B65: P2543 | C65: 46058 | D65: 14:45 | E65: Cancelled | H65: D07 | I65: DR138 | J65: DG16 | K65: Surgery | L65: Emergency Walk-in | R65: IP06 | S65: Not Applicable | V65: No | X65: Not Required | Z65: Not Treated | AA65: =VLOOKUP(H65,Departments!$A:$B,2,0) -> Pediatrics | AB65: =VLOOKUP(J65,Diagnosis_Guide!$A:$B,2,0) -> Pediatric Asthma | AC65: =VLOOKUP(J65,Diagnosis_Guide!$A:$C,3,0) -> Pediatric | AD65: =VLOOKUP(R65,Insurance_Plans!$A:$C,3,0) -> Public | AE65: =IF(Q65="","",Q65*0.05) | AF65: =IF(Q65="","",Q65+AE65) | AG65: =IF(U65="","Not Available",IF(U65>=4,"High",IF(U65=3,"Medium","Low"))) -> Not Available
A66: V10065 | B66: P2371 | C66: 46060 | D66: 08:00 | E66: Attended | F66: 46060 | G66: 46060 | H66: D01 | I66: DR104 | J66: DG28 | K66: Outpatient | L66: Doctor Referral | M66: 42400 | N66: 7550 | O66: 10450 | P66: 0 | Q66: 62900 | R66: IP05 | S66: Not Applicable | T66: 62900 | U66: 5 | V66: No | X66: Not Required | Y66: No | Z66: Improved | AA66: =VLOOKUP(H66,Departments!$A:$B,2,0) -> Emergency | AB66: =VLOOKUP(J66,Diagnosis_Guide!$A:$B,2,0) -> Trauma Observation | AC66: =VLOOKUP(J66,Diagnosis_Guide!$A:$C,3,0) -> Emergency | AD66: =VLOOKUP(R66,Insurance_Plans!$A:$C,3,0) -> Self-Pay | AE66: =IF(Q66="","",Q66*0.05) -> 3145 | AF66: =IF(Q66="","",Q66+AE66) -> 66045 | AG66: =IF(U66="","Not Available",IF(U66>=4,"High",IF(U66=3,"Medium","Low"))) -> High
A67: V10066 | B67: P2541 | C67: 46126 | D67: 15:15 | E67: Cancelled | H67: D07 | I67: DR138 | J67: DG18 | K67: Inpatient | L67: Emergency Walk-in | R67: IP03 | S67: Not Applicable | V67: No | X67: Not Required | Z67: Not Treated | AA67: =VLOOKUP(H67,Departments!$A:$B,2,0) -> Pediatrics | AB67: =VLOOKUP(J67,Diagnosis_Guide!$A:$B,2,0) -> Neonatal Observation | AC67: =VLOOKUP(J67,Diagnosis_Guide!$A:$C,3,0) -> Pediatric | AD67: =VLOOKUP(R67,Insurance_Plans!$A:$C,3,0) -> Private | AE67: =IF(Q67="","",Q67*0.05) | AF67: =IF(Q67="","",Q67+AE67) | AG67: =IF(U67="","Not Available",IF(U67>=4,"High",IF(U67=3,"Medium","Low"))) -> Not Available
A68: V10067 | B68: P2415 | C68: 46044 | D68: 08:30 | E68: Attended | F68: 46044 | G68: 46046 | H68: D09 | I68: DR151 | J68: DG24 | K68: Emergency | L68: Scheduled Appointment | M68: 6500 | N68: 850 | O68: 950 | P68: 7000 | Q68: 16500 | R68: IP05 | S68: Not Applicable | T68: 16500 | U68: 3 | V68: Yes | W68: 46053 | X68: No | Y68: No | Z68: Stable | AA68: =VLOOKUP(H68,Departments!$A:$B,2,0) -> Pulmonology | AB68: =VLOOKUP(J68,Diagnosis_Guide!$A:$B,2,0) -> Acute Bronchitis | AC68: =VLOOKUP(J68,Diagnosis_Guide!$A:$C,3,0) -> Respiratory | AD68: =VLOOKUP(R68,Insurance_Plans!$A:$C,3,0) -> Self-Pay | AE68: =IF(Q68="","",Q68*0.05) -> 825 | AF68: =IF(Q68="","",Q68+AE68) -> 17325 | AG68: =IF(U68="","Not Available",IF(U68>=4,"High",IF(U68=3,"Medium","Low"))) -> Medium
A69: V10068 | B69: P2062 | C69: 46152 | D69: 13:00 | E69: Attended | F69: 46152 | G69: 46152 | H69: D01 | I69: DR103 | J69: DG28 | K69: Emergency | L69: Emergency Walk-in | M69: 44900 | N69: 6150 | O69: 10500 | P69: 0 | Q69: 62550 | R69: IP04 | S69: Approved | T69: 16540 | U69: 5 | V69: Yes | W69: 46164 | X69: Yes | Y69: No | Z69: Improved | AA69: =VLOOKUP(H69,Departments!$A:$B,2,0) -> Emergency | AB69: =VLOOKUP(J69,Diagnosis_Guide!$A:$B,2,0) -> Trauma Observation | AC69: =VLOOKUP(J69,Diagnosis_Guide!$A:$C,3,0) -> Emergency | AD69: =VLOOKUP(R69,Insurance_Plans!$A:$C,3,0) -> Employer | AE69: =IF(Q69="","",Q69*0.05) -> 3127.5 | AF69: =IF(Q69="","",Q69+AE69) -> 65677.5 | AG69: =IF(U69="","Not Available",IF(U69>=4,"High",IF(U69=3,"Medium","Low"))) -> High
A70: V10069 | B70: P2597 | C70: 46139 | D70: 09:15 | E70: Attended | F70: 46139 | G70: 46148 | H70: D04 | I70: DR121 | J70: DG09 | K70: Emergency | L70: Doctor Referral | M70: 80900 | N70: 8200 | O70: 9050 | P70: 54000 | Q70: 153650 | R70: IP03 | S70: Approved | T70: 24250 | U70: 4 | V70: Yes | W70: 46168 | X70: Yes | Y70: No | Z70: Improved | AA70: =VLOOKUP(H70,Departments!$A:$B,2,0) -> Orthopedics | AB70: =VLOOKUP(J70,Diagnosis_Guide!$A:$B,2,0) -> Spinal Injury | AC70: =VLOOKUP(J70,Diagnosis_Guide!$A:$C,3,0) -> Musculoskeletal | AD70: =VLOOKUP(R70,Insurance_Plans!$A:$C,3,0) -> Private | AE70: =IF(Q70="","",Q70*0.05) -> 7682.5 | AF70: =IF(Q70="","",Q70+AE70) -> 161332.5 | AG70: =IF(U70="","Not Available",IF(U70>=4,"High",IF(U70=3,"Medium","Low"))) -> High
A71: V10070 | B71: P2167 | C71: 46147 | D71: 15:15 | E71: Rescheduled | H71: D03 | I71: DR114 | J71: DG05 | K71: Inpatient | L71: Emergency Walk-in | R71: IP06 | S71: Not Applicable | V71: No | X71: Not Required | Z71: Not Treated | AA71: =VLOOKUP(H71,Departments!$A:$B,2,0) -> Neurology | AB71: =VLOOKUP(J71,Diagnosis_Guide!$A:$B,2,0) -> Migraine Complication | AC71: =VLOOKUP(J71,Diagnosis_Guide!$A:$C,3,0) -> Neurological | AD71: =VLOOKUP(R71,Insurance_Plans!$A:$C,3,0) -> Public | AE71: =IF(Q71="","",Q71*0.05) | AF71: =IF(Q71="","",Q71+AE71) | AG71: =IF(U71="","Not Available",IF(U71>=4,"High",IF(U71=3,"Medium","Low"))) -> Not Available
A72: V10071 | B72: P2218 | C72: 46063 | D72: 16:30 | E72: Canceled | H72: D06 | I72: DR131 | J72: DG15 | K72: Surgery | L72: Emergency Walk-in | R72: IP03 | S72: Not Applicable | V72: No | X72: Not Required | Z72: Not Treated | AA72: =VLOOKUP(H72,Departments!$A:$B,2,0) -> Surgery | AB72: =VLOOKUP(J72,Diagnosis_Guide!$A:$B,2,0) -> Post-Operative Infection | AC72: =VLOOKUP(J72,Diagnosis_Guide!$A:$C,3,0) -> Surgical | AD72: =VLOOKUP(R72,Insurance_Plans!$A:$C,3,0) -> Private | AE72: =IF(Q72="","",Q72*0.05) | AF72: =IF(Q72="","",Q72+AE72) | AG72: =IF(U72="","Not Available",IF(U72>=4,"High",IF(U72=3,"Medium","Low"))) -> Not Available
A73: V10072 | B73: P2042 | C73: 46118 | D73: 12:30 | E73: Attended | F73: 46118 | G73: 46120 | H73: D07 | I73: DR137 | J73: DG17 | K73: Inpatient | L73: Scheduled Appointment | M73: 6700 | N73: 750 | O73: 950 | P73: 6000 | Q73: 16200 | R73: IP05 | S73: Not Applicable | T73: 16200 | U73: 4 | V73: No | X73: Not Required | Y73: No | Z73: Recovered | AA73: =VLOOKUP(H73,Departments!$A:$B,2,0) -> Pediatrics | AB73: =VLOOKUP(J73,Diagnosis_Guide!$A:$B,2,0) -> Child Fever | AC73: =VLOOKUP(J73,Diagnosis_Guide!$A:$C,3,0) -> Pediatric | AD73: =VLOOKUP(R73,Insurance_Plans!$A:$C,3,0) -> Self-Pay | AE73: =IF(Q73="","",Q73*0.05) -> 810 | AF73: =IF(Q73="","",Q73+AE73) -> 17010 | AG73: =IF(U73="","Not Available",IF(U73>=4,"High",IF(U73=3,"Medium","Low"))) -> High
A74: V10073 | B74: P2346 | C74: 46056 | D74: 10:45 | E74: Attended | F74: 46056 | G74: 46056 | H74: D09 | I74: DR152 | J74: DG24 | K74: Inpatient | L74: Doctor Referral | M74: 6800 | N74: 950 | O74: 1300 | P74: 0 | Q74: 11550 | R74: IP02 | S74: Pending | T74: 4740 | U74: 4 | V74: Yes | W74: 46063 | X74: No | Y74: No | Z74: Stable | AA74: =VLOOKUP(H74,Departments!$A:$B,2,0) -> Pulmonology | AB74: =VLOOKUP(J74,Diagnosis_Guide!$A:$B,2,0) -> Acute Bronchitis | AC74: =VLOOKUP(J74,Diagnosis_Guide!$A:$C,3,0) -> Respiratory | AD74: =VLOOKUP(R74,Insurance_Plans!$A:$C,3,0) -> Private | AE74: =IF(Q74="","",Q74*0.05) -> 577.5 | AF74: =IF(Q74="","",Q74+AE74) -> 12127.5 | AG74: =IF(U74="","Not Available",IF(U74>=4,"High",IF(U74=3,"Medium","Low"))) -> High
A75: V10074 | B75: P2317 | C75: 46166 | D75: 09:15 | E75: Rescheduled | H75: D08 | I75: DR143 | J75: DG19 | K75: Inpatient | L75: Scheduled Appointment | R75: IP05 | S75: Not Applicable | V75: No | X75: Not Required | Z75: Not Treated | AA75: =VLOOKUP(H75,Departments!$A:$B,2,0) -> Nephrology | AB75: =VLOOKUP(J75,Diagnosis_Guide!$A:$B,2,0) -> Kidney Stone | AC75: =VLOOKUP(J75,Diagnosis_Guide!$A:$C,3,0) -> Renal | AD75: =VLOOKUP(R75,Insurance_Plans!$A:$C,3,0) -> Self-Pay | AE75: =IF(Q75="","",Q75*0.05) | AF75: =IF(Q75="","",Q75+AE75) | AG75: =IF(U75="","Not Available",IF(U75>=4,"High",IF(U75=3,"Medium","Low"))) -> Not Available
A76: V10075 | B76: P2535 | C76: 46151 | D76: 08:00 | E76: Attended | F76: 46151 | G76: 46153 | H76: D04 | I76: DR122 | J76: DG08 | K76: Inpatient | L76: Transfer from Clinic | M76: 8000 | N76: 1350 | O76: 1350 | P76: 12000 | Q76: 25200 | R76: IP04 | S76: Approved | T76: 7200 | U76: 3 | V76: Yes | W76: 46173 | X76: No | Y76: No | Z76: Stable | AA76: =VLOOKUP(H76,Departments!$A:$B,2,0) -> Orthopedics | AB76: =VLOOKUP(J76,Diagnosis_Guide!$A:$B,2,0) -> Joint Pain | AC76: =VLOOKUP(J76,Diagnosis_Guide!$A:$C,3,0) -> Musculoskeletal | AD76: =VLOOKUP(R76,Insurance_Plans!$A:$C,3,0) -> Employer | AE76: =IF(Q76="","",Q76*0.05) -> 1260 | AF76: =IF(Q76="","",Q76+AE76) -> 26460 | AG76: =IF(U76="","Not Available",IF(U76>=4,"High",IF(U76=3,"Medium","Low"))) -> Medium
A77: V10076 | B77: P2102 | C77: 46059 | D77: 10:30 | E77: Attended | F77: 46059 | G77: 46059 | H77: D07 | I77: DR139 | J77: DG18 | K77: Outpatient | L77: Transfer from Clinic | M77: 37200 | N77: 4100 | O77: 4250 | P77: 0 | Q77: 47350 | R77: IP01 | S77: Pending | T77: 21610 | U77: 3 | V77: Yes | W77: 46079 | X77: No | Y77: Yes | Z77: Improved | AA77: =VLOOKUP(H77,Departments!$A:$B,2,0) -> Pediatrics | AB77: =VLOOKUP(J77,Diagnosis_Guide!$A:$B,2,0) -> Neonatal Observation | AC77: =VLOOKUP(J77,Diagnosis_Guide!$A:$C,3,0) -> Pediatric | AD77: =VLOOKUP(R77,Insurance_Plans!$A:$C,3,0) -> Public | AE77: =IF(Q77="","",Q77*0.05) -> 2367.5 | AF77: =IF(Q77="","",Q77+AE77) -> 49717.5 | AG77: =IF(U77="","Not Available",IF(U77>=4,"High",IF(U77=3,"Medium","Low"))) -> Medium
A78: V10077 | B78: P2118 | C78: 46141 | D78: 16:45 | E78: Attended | F78: 46141 | G78: 46141 | H78: D05 | I78: DR127 | J78: DG10 | K78: Outpatient | L78: Scheduled Appointment | M78: 5200 | N78: 700 | O78: 1150 | P78: 0 | Q78: 8550 | R78: IP02 | S78: Approved | T78: 3690 | U78: 5 | V78: Yes | W78: 46158 | X78: Yes | Y78: No | Z78: Against Medical Advice | AA78: =VLOOKUP(H78,Departments!$A:$B,2,0) -> General Medicine | AB78: =VLOOKUP(J78,Diagnosis_Guide!$A:$B,2,0) -> Fever Investigation | AC78: =VLOOKUP(J78,Diagnosis_Guide!$A:$C,3,0) -> Infectious/General | AD78: =VLOOKUP(R78,Insurance_Plans!$A:$C,3,0) -> Private | AE78: =IF(Q78="","",Q78*0.05) -> 427.5 | AF78: =IF(Q78="","",Q78+AE78) -> 8977.5 | AG78: =IF(U78="","Not Available",IF(U78>=4,"High",IF(U78=3,"Medium","Low"))) -> High
A79: V10078 | B79: P2569 | C79: 46141 | D79: 17:30 | E79: Attended | F79: 46141 | G79: 46148 | H79: D06 | I79: DR131 | J79: DG14 | K79: Surgery | L79: Scheduled Appointment | M79: 64600 | N79: 10600 | O79: 10150 | P79: 24500 | Q79: 110650 | R79: IP05 | S79: Not Applicable | T79: 110650 | U79: 3 | V79: Yes | W79: 46168 | X79: Yes | Y79: Yes | Z79: Recovered | AA79: =VLOOKUP(H79,Departments!$A:$B,2,0) -> Surgery | AB79: =VLOOKUP(J79,Diagnosis_Guide!$A:$B,2,0) -> Gallbladder Surgery | AC79: =VLOOKUP(J79,Diagnosis_Guide!$A:$C,3,0) -> Surgical | AD79: =VLOOKUP(R79,Insurance_Plans!$A:$C,3,0) -> Self-Pay | AE79: =IF(Q79="","",Q79*0.05) -> 5532.5 | AF79: =IF(Q79="","",Q79+AE79) -> 116182.5 | AG79: =IF(U79="","Not Available",IF(U79>=4,"High",IF(U79=3,"Medium","Low"))) -> Medium
A80: V10079 | B80: P2570 | C80: 46076 | D80: 17:30 | E80: Cancelled | H80: D01 | I80: DR104 | J80: DG30 | K80: Outpatient | L80: Scheduled Appointment | R80: IP03 | S80: Not Applicable | V80: No | X80: Not Required | Z80: Not Treated | AA80: =VLOOKUP(H80,Departments!$A:$B,2,0) -> Emergency | AB80: =VLOOKUP(J80,Diagnosis_Guide!$A:$B,2,0) -> Food Poisoning | AC80: =VLOOKUP(J80,Diagnosis_Guide!$A:$C,3,0) -> Emergency | AD80: =VLOOKUP(R80,Insurance_Plans!$A:$C,3,0) -> Private | AE80: =IF(Q80="","",Q80*0.05) | AF80: =IF(Q80="","",Q80+AE80) | AG80: =IF(U80="","Not Available",IF(U80>=4,"High",IF(U80=3,"Medium","Low"))) -> Not Available
A81: V10080 | B81: P2252 | C81: 46110 | D81: 11:45 | E81: Rescheduled | H81: D08 | I81: DR145 | J81: DG21 | K81: Outpatient | L81: Scheduled Appointment | R81: IP02 | S81: Not Applicable | V81: No | X81: Not Required | Z81: Not Treated | AA81: =VLOOKUP(H81,Departments!$A:$B,2,0) -> Nephrology | AB81: =VLOOKUP(J81,Diagnosis_Guide!$A:$B,2,0) -> Dialysis Complication | AC81: =VLOOKUP(J81,Diagnosis_Guide!$A:$C,3,0) -> Renal | AD81: =VLOOKUP(R81,Insurance_Plans!$A:$C,3,0) -> Private | AE81: =IF(Q81="","",Q81*0.05) | AF81: =IF(Q81="","",Q81+AE81) | AG81: =IF(U81="","Not Available",IF(U81>=4,"High",IF(U81=3,"Medium","Low"))) -> Not Available
A82: V10081 | B82: P2003 | C82: 46025 | D82: 10:45 | E82: Attended | F82: 46026 | G82: 46029 | H82: D08 | I82: DR143 | J82: DG20 | K82: Emergency | L82: Emergency Walk-in | M82: 60200 | N82: 5000 | O82: 13550 | P82: 13500 | Q82: 93050 | R82: IP04 | S82: Approved | T82: 24160 | U82: 4 | V82: No | X82: Not Required | Y82: No | Z82: Stable | AA82: =VLOOKUP(H82,Departments!$A:$B,2,0) -> Nephrology | AB82: =VLOOKUP(J82,Diagnosis_Guide!$A:$B,2,0) -> Chronic Kidney Disease | AC82: =VLOOKUP(J82,Diagnosis_Guide!$A:$C,3,0) -> Renal | AD82: =VLOOKUP(R82,Insurance_Plans!$A:$C,3,0) -> Employer | AE82: =IF(Q82="","",Q82*0.05) -> 4652.5 | AF82: =IF(Q82="","",Q82+AE82) -> 97702.5 | AG82: =IF(U82="","Not Available",IF(U82>=4,"High",IF(U82=3,"Medium","Low"))) -> High
A83: V10082 | B83: P2198 | C83: 46028 | D83: 12:30 | E83: Attended | F83: 46028 | G83: 46029 | H83: D04 | I83: DR120 | J83: DG08 | K83: Emergency | L83: Scheduled Appointment | M83: 8000 | N83: 1050 | O83: 1250 | P83: 3500 | Q83: 14600 | R83: IP03 | S83: Approved | T83: 3390 | U83: 5 | V83: Yes | W83: 46036 | X83: Yes | Y83: No | Z83: Recovered | AA83: =VLOOKUP(H83,Departments!$A:$B,2,0) -> Orthopedics | AB83: =VLOOKUP(J83,Diagnosis_Guide!$A:$B,2,0) -> Joint Pain | AC83: =VLOOKUP(J83,Diagnosis_Guide!$A:$C,3,0) -> Musculoskeletal | AD83: =VLOOKUP(R83,Insurance_Plans!$A:$C,3,0) -> Private | AE83: =IF(Q83="","",Q83*0.05) -> 730 | AF83: =IF(Q83="","",Q83+AE83) -> 15330 | AG83: =IF(U83="","Not Available",IF(U83>=4,"High",IF(U83=3,"Medium","Low"))) -> High
A84: V10083 | B84: P2580 | C84: 46167 | D84: 10:00 | E84: Attended | F84: 46167 | G84: 46176 | H84: D09 | I84: DR153 | J84: DG22 | K84: Emergency | L84: Doctor Referral | M84: 34300 | N84: 6050 | O84: 6900 | P84: 54000 | Q84: 103250 | R84: IP02 | S84: Approved | T84: 36840 | U84: 2 | V84: Yes | W84: 46189 | X84: Yes | Y84: No | Z84: Recovered | AA84: =VLOOKUP(H84,Departments!$A:$B,2,0) -> Pulmonology | AB84: =VLOOKUP(J84,Diagnosis_Guide!$A:$B,2,0) -> Pneumonia | AC84: =VLOOKUP(J84,Diagnosis_Guide!$A:$C,3,0) -> Respiratory | AD84: =VLOOKUP(R84,Insurance_Plans!$A:$C,3,0) -> Private | AE84: =IF(Q84="","",Q84*0.05) -> 5162.5 | AF84: =IF(Q84="","",Q84+AE84) -> 108412.5 | AG84: =IF(U84="","Not Available",IF(U84>=4,"High",IF(U84=3,"Medium","Low"))) -> Low
A85: V10084 | B85: P2531 | C85: 46155 | D85: 08:15 | E85: Attended | F85: 46155 | G85: 46156 | H85: D07 | I85: DR139 | J85: DG16 | K85: Surgery | L85: Emergency Walk-in | M85: 11200 | N85: 1100 | O85: 1250 | P85: 6000 | Q85: 21350 | R85: IP05 | S85: Not Applicable | T85: 21350 | U85: 5 | V85: No | X85: Not Required | Y85: No | Z85: Stable | AA85: =VLOOKUP(H85,Departments!$A:$B,2,0) -> Pediatrics | AB85: =VLOOKUP(J85,Diagnosis_Guide!$A:$B,2,0) -> Pediatric Asthma | AC85: =VLOOKUP(J85,Diagnosis_Guide!$A:$C,3,0) -> Pediatric | AD85: =VLOOKUP(R85,Insurance_Plans!$A:$C,3,0) -> Self-Pay | AE85: =IF(Q85="","",Q85*0.05) -> 1067.5 | AF85: =IF(Q85="","",Q85+AE85) -> 22417.5 | AG85: =IF(U85="","Not Available",IF(U85>=4,"High",IF(U85=3,"Medium","Low"))) -> High
A86: V10085 | B86: P2100 | C86: 46029 | D86: 17:30 | E86: Missed | H86: D02 | I86: DR110 | J86: DG01 | K86: Outpatient | L86: Emergency Walk-in | R86: IP01 | S86: Not Applicable | V86: No | X86: Not Required | Z86: Not Treated | AA86: =VLOOKUP(H86,Departments!$A:$B,2,0) -> Cardiology | AB86: =VLOOKUP(J86,Diagnosis_Guide!$A:$B,2,0) -> Chest Pain | AC86: =VLOOKUP(J86,Diagnosis_Guide!$A:$C,3,0) -> Cardiovascular | AD86: =VLOOKUP(R86,Insurance_Plans!$A:$C,3,0) -> Public | AE86: =IF(Q86="","",Q86*0.05) | AF86: =IF(Q86="","",Q86+AE86) | AG86: =IF(U86="","Not Available",IF(U86>=4,"High",IF(U86=3,"Medium","Low"))) -> Not Available
A87: V10086 | B87: P2342 | C87: 46041 | D87: 17:45 | E87: Attended | F87: 46041 | G87: 46046 | H87: D07 | I87: DR138 | J87: DG17 | K87: Inpatient | L87: Scheduled Appointment | M87: 5200 | N87: 900 | O87: 1050 | P87: 15000 | Q87: 24650 | R87: IP01 | S87: Pending | T87: 11390 | U87: 1 | V87: Yes | W87: 46062 | X87: Yes | Y87: Yes | Z87: Recovered | AA87: =VLOOKUP(H87,Departments!$A:$B,2,0) -> Pediatrics | AB87: =VLOOKUP(J87,Diagnosis_Guide!$A:$B,2,0) -> Child Fever | AC87: =VLOOKUP(J87,Diagnosis_Guide!$A:$C,3,0) -> Pediatric | AD87: =VLOOKUP(R87,Insurance_Plans!$A:$C,3,0) -> Public | AE87: =IF(Q87="","",Q87*0.05) -> 1232.5 | AF87: =IF(Q87="","",Q87+AE87) -> 25882.5 | AG87: =IF(U87="","Not Available",IF(U87>=4,"High",IF(U87=3,"Medium","Low"))) -> Low
A88: V10087 | B88: P2239 | C88: 46025 | D88: 15:45 | E88: Attended | F88: 46025 | G88: 46026 | H88: D09 | I88: DR154 | J88: DG24 | K88: Inpatient | L88: Scheduled Appointment | M88: 9000 | N88: 1550 | O88: 1950 | P88: 4500 | Q88: 17800 | R88: IP03 | S88: Approved | T88: 3870 | U88: 3 | V88: Yes | W88: 46033 | X88: Yes | Y88: Yes | Z88: Recovered | AA88: =VLOOKUP(H88,Departments!$A:$B,2,0) -> Pulmonology | AB88: =VLOOKUP(J88,Diagnosis_Guide!$A:$B,2,0) -> Acute Bronchitis | AC88: =VLOOKUP(J88,Diagnosis_Guide!$A:$C,3,0) -> Respiratory | AD88: =VLOOKUP(R88,Insurance_Plans!$A:$C,3,0) -> Private | AE88: =IF(Q88="","",Q88*0.05) -> 890 | AF88: =IF(Q88="","",Q88+AE88) -> 18690 | AG88: =IF(U88="","Not Available",IF(U88>=4,"High",IF(U88=3,"Medium","Low"))) -> Medium
A89: V10088 | B89: P2456 | C89: 46034 | D89: 08:15 | E89: Attended | F89: 46034 | G89: 46039 | H89: D03 | I89: DR114 | J89: DG04 | K89: Inpatient | L89: Transfer from Clinic | M89: 65400 | N89: 7250 | O89: 9900 | P89: 17500 | Q89: 101050 | R89: IP07 | S89: Approved | T89: 55780 | U89: 5 | V89: Yes | W89: 46048 | X89: Yes | Y89: No | Z89: Improved | AA89: =VLOOKUP(H89,Departments!$A:$B,2,0) -> Neurology | AB89: =VLOOKUP(J89,Diagnosis_Guide!$A:$B,2,0) -> Stroke Assessment | AC89: =VLOOKUP(J89,Diagnosis_Guide!$A:$C,3,0) -> Neurological | AD89: =VLOOKUP(R89,Insurance_Plans!$A:$C,3,0) -> Community | AE89: =IF(Q89="","",Q89*0.05) -> 5052.5 | AF89: =IF(Q89="","",Q89+AE89) -> 106102.5 | AG89: =IF(U89="","Not Available",IF(U89>=4,"High",IF(U89=3,"Medium","Low"))) -> High
A90: V10089 | B90: P2071 | C90: 46144 | D90: 15:30 | E90: No Show | H90: D05 | I90: DR130 | J90: DG12 | K90: Outpatient | L90: Emergency Walk-in | R90: IP03 | S90: Not Applicable | V90: No | X90: Not Required | Z90: Not Treated | AA90: =VLOOKUP(H90,Departments!$A:$B,2,0) -> General Medicine | AB90: =VLOOKUP(J90,Diagnosis_Guide!$A:$B,2,0) -> Severe Infection | AC90: =VLOOKUP(J90,Diagnosis_Guide!$A:$C,3,0) -> Infectious/General | AD90: =VLOOKUP(R90,Insurance_Plans!$A:$C,3,0) -> Private | AE90: =IF(Q90="","",Q90*0.05) | AF90: =IF(Q90="","",Q90+AE90) | AG90: =IF(U90="","Not Available",IF(U90>=4,"High",IF(U90=3,"Medium","Low"))) -> Not Available
A91: V10090 | B91: P2167 | C91: 46149 | D91: 11:00 | E91: Attended | F91: 46149 | G91: 46161 | H91: D03 | I91: DR113 | J91: DG04 | K91: Emergency | L91: Emergency Walk-in | M91: 70800 | N91: 11450 | O91: 15650 | P91: 54000 | Q91: 154400 | R91: IP01 | S91: Approved | T91: 69780 | U91: 1 | V91: No | X91: Not Required | Y91: Yes | Z91: Recovered | AA91: =VLOOKUP(H91,Departments!$A:$B,2,0) -> Neurology | AB91: =VLOOKUP(J91,Diagnosis_Guide!$A:$B,2,0) -> Stroke Assessment | AC91: =VLOOKUP(J91,Diagnosis_Guide!$A:$C,3,0) -> Neurological | AD91: =VLOOKUP(R91,Insurance_Plans!$A:$C,3,0) -> Public | AE91: =IF(Q91="","",Q91*0.05) -> 7720 | AF91: =IF(Q91="","",Q91+AE91) -> 162120 | AG91: =IF(U91="","Not Available",IF(U91>=4,"High",IF(U91=3,"Medium","Low"))) -> Low
A92: V10091 | B92: P2369 | C92: 46073 | D92: 11:30 | E92: Attended | F92: 46073 | G92: 46080 | H92: D02 | I92: DR107 | J92: DG02 | K92: Emergency | L92: Scheduled Appointment | M92: 59100 | N92: 10100 | O92: 6100 | P92: 21000 | Q92: 97800 | R92: IP02 | S92: Pending | T92: 34930 | U92: 4 | V92: Yes | W92: 46101 | X92: Yes | Y92: No | Z92: Improved | AA92: =VLOOKUP(H92,Departments!$A:$B,2,0) -> Cardiology | AB92: =VLOOKUP(J92,Diagnosis_Guide!$A:$B,2,0) -> Heart Failure | AC92: =VLOOKUP(J92,Diagnosis_Guide!$A:$C,3,0) -> Cardiovascular | AD92: =VLOOKUP(R92,Insurance_Plans!$A:$C,3,0) -> Private | AE92: =IF(Q92="","",Q92*0.05) -> 4890 | AF92: =IF(Q92="","",Q92+AE92) -> 102690 | AG92: =IF(U92="","Not Available",IF(U92>=4,"High",IF(U92=3,"Medium","Low"))) -> High
A93: V10092 | B93: P2445 | C93: 46053 | D93: 10:15 | E93: Missed | H93: D10 | I93: DR155 | J93: DG27 | K93: Emergency | L93: Emergency Walk-in | R93: IP04 | S93: Not Applicable | V93: No | X93: Not Required | Z93: Not Treated | AA93: =VLOOKUP(H93,Departments!$A:$B,2,0) -> Obstetrics | AB93: =VLOOKUP(J93,Diagnosis_Guide!$A:$B,2,0) -> Emergency C-Section | AC93: =VLOOKUP(J93,Diagnosis_Guide!$A:$C,3,0) -> Maternal Health | AD93: =VLOOKUP(R93,Insurance_Plans!$A:$C,3,0) -> Employer | AE93: =IF(Q93="","",Q93*0.05) | AF93: =IF(Q93="","",Q93+AE93) | AG93: =IF(U93="","Not Available",IF(U93>=4,"High",IF(U93=3,"Medium","Low"))) -> Not Available
A94: V10093 | B94: P2251 | C94: 46071 | D94: 16:30 | E94: No Show | H94: D01 | I94: DR105 | J94: DG29 | K94: Inpatient | L94: Scheduled Appointment | R94: IP07 | S94: Not Applicable | V94: No | X94: Not Required | Z94: Not Treated | AA94: =VLOOKUP(H94,Departments!$A:$B,2,0) -> Emergency | AB94: =VLOOKUP(J94,Diagnosis_Guide!$A:$B,2,0) -> Accident Injury | AC94: =VLOOKUP(J94,Diagnosis_Guide!$A:$C,3,0) -> Emergency | AD94: =VLOOKUP(R94,Insurance_Plans!$A:$C,3,0) -> Community | AE94: =IF(Q94="","",Q94*0.05) | AF94: =IF(Q94="","",Q94+AE94) | AG94: =IF(U94="","Not Available",IF(U94>=4,"High",IF(U94=3,"Medium","Low"))) -> Not Available
A95: V10094 | B95: P2521 | C95: 46076 | D95: 09:45 | E95: No Show | H95: D01 | I95: DR104 | J95: DG30 | K95: Emergency | L95: Scheduled Appointment | R95: IP07 | S95: Not Applicable | V95: No | X95: Not Required | Z95: Not Treated | AA95: =VLOOKUP(H95,Departments!$A:$B,2,0) -> Emergency | AB95: =VLOOKUP(J95,Diagnosis_Guide!$A:$B,2,0) -> Food Poisoning | AC95: =VLOOKUP(J95,Diagnosis_Guide!$A:$C,3,0) -> Emergency | AD95: =VLOOKUP(R95,Insurance_Plans!$A:$C,3,0) -> Community | AE95: =IF(Q95="","",Q95*0.05) | AF95: =IF(Q95="","",Q95+AE95) | AG95: =IF(U95="","Not Available",IF(U95>=4,"High",IF(U95=3,"Medium","Low"))) -> Not Available
A96: V10095 | B96: P2522 | C96: 46141 | D96: 10:30 | E96: Attended | F96: 46142 | G96: 46144 | H96: D05 | I96: DR129 | J96: DG11 | K96: Inpatient | L96: Emergency Walk-in | M96: 27800 | N96: 3850 | O96: 5450 | P96: 12000 | Q96: 51100 | R96: IP04 | S96: Approved | T96: 13680 | U96: 4 | V96: No | X96: Not Required | Y96: No | Z96: Stable | AA96: =VLOOKUP(H96,Departments!$A:$B,2,0) -> General Medicine | AB96: =VLOOKUP(J96,Diagnosis_Guide!$A:$B,2,0) -> Diabetes Complication | AC96: =VLOOKUP(J96,Diagnosis_Guide!$A:$C,3,0) -> Endocrine/General | AD96: =VLOOKUP(R96,Insurance_Plans!$A:$C,3,0) -> Employer | AE96: =IF(Q96="","",Q96*0.05) -> 2555 | AF96: =IF(Q96="","",Q96+AE96) -> 53655 | AG96: =IF(U96="","Not Available",IF(U96>=4,"High",IF(U96=3,"Medium","Low"))) -> High
A97: V10096 | B97: P2564 | C97: 46098 | D97: 15:30 | E97: Attended | F97: 46098 | G97: 46099 | H97: D02 | I97: DR107 | J97: DG02 | K97: Outpatient | L97: Emergency Walk-in | M97: 45500 | N97: 5400 | O97: 5800 | P97: 3000 | Q97: 61200 | R97: IP02 | S97: Approved | T97: 22120 | U97: 5 | V97: Yes | W97: 46114 | X97: Yes | Y97: No | Z97: Recovered | AA97: =VLOOKUP(H97,Departments!$A:$B,2,0) -> Cardiology | AB97: =VLOOKUP(J97,Diagnosis_Guide!$A:$B,2,0) -> Heart Failure | AC97: =VLOOKUP(J97,Diagnosis_Guide!$A:$C,3,0) -> Cardiovascular | AD97: =VLOOKUP(R97,Insurance_Plans!$A:$C,3,0) -> Private | AE97: =IF(Q97="","",Q97*0.05) -> 3060 | AF97: =IF(Q97="","",Q97+AE97) -> 64260 | AG97: =IF(U97="","Not Available",IF(U97>=4,"High",IF(U97=3,"Medium","Low"))) -> High
A98: V10097 | B98: P2202 | C98: 46100 | D98: 12:15 | E98: Attended | F98: 46100 | G98: 46107 | H98: D08 | I98: DR145 | J98: DG21 | K98: Surgery | L98: Transfer from Clinic | M98: 50700 | N98: 5800 | O98: 12650 | P98: 31500 | Q98: 101450 | R98: IP05 | S98: Not Applicable | T98: 101450 | U98: 3 | V98: Yes | W98: 46114 | X98: Yes | Y98: No | Z98: Recovered | AA98: =VLOOKUP(H98,Departments!$A:$B,2,0) -> Nephrology | AB98: =VLOOKUP(J98,Diagnosis_Guide!$A:$B,2,0) -> Dialysis Complication | AC98: =VLOOKUP(J98,Diagnosis_Guide!$A:$C,3,0) -> Renal | AD98: =VLOOKUP(R98,Insurance_Plans!$A:$C,3,0) -> Self-Pay | AE98: =IF(Q98="","",Q98*0.05) -> 5072.5 | AF98: =IF(Q98="","",Q98+AE98) -> 106522.5 | AG98: =IF(U98="","Not Available",IF(U98>=4,"High",IF(U98=3,"Medium","Low"))) -> Medium
A99: V10098 | B99: P2566 | C99: 46141 | D99: 13:00 | E99: Attended | F99: 46142 | G99: 46142 | H99: D10 | I99: DR160 | J99: DG25 | K99: Outpatient | L99: Scheduled Appointment | M99: 22400 | N99: 3100 | O99: 2650 | P99: 0 | Q99: 29150 | R99: IP06 | S99: Approved | T99: 9150 | U99: 5 | V99: No | X99: Not Required | Y99: No | Z99: Improved | AA99: =VLOOKUP(H99,Departments!$A:$B,2,0) -> Obstetrics | AB99: =VLOOKUP(J99,Diagnosis_Guide!$A:$B,2,0) -> Antenatal Complication | AC99: =VLOOKUP(J99,Diagnosis_Guide!$A:$C,3,0) -> Maternal Health | AD99: =VLOOKUP(R99,Insurance_Plans!$A:$C,3,0) -> Public | AE99: =IF(Q99="","",Q99*0.05) -> 1457.5 | AF99: =IF(Q99="","",Q99+AE99) -> 30607.5 | AG99: =IF(U99="","Not Available",IF(U99>=4,"High",IF(U99=3,"Medium","Low"))) -> High
A100: V10099 | B100: P2307 | C100: 46168 | D100: 08:15 | E100: Attended | F100: 46169 | G100: 46174 | H100: D05 | I100: DR125 | J100: DG11 | K100: Surgery | L100: Emergency Walk-in | M100: 27400 | N100: 2750 | O100: 4350 | P100: 30000 | Q100: 65700 | R100: IP02 | S100: Approved | T100: 23700 | U100: 4 | V100: Yes | W100: 46188 | X100: Yes | Y100: No | Z100: Improved | AA100: =VLOOKUP(H100,Departments!$A:$B,2,0) -> General Medicine | AB100: =VLOOKUP(J100,Diagnosis_Guide!$A:$B,2,0) -> Diabetes Complication | AC100: =VLOOKUP(J100,Diagnosis_Guide!$A:$C,3,0) -> Endocrine/General | AD100: =VLOOKUP(R100,Insurance_Plans!$A:$C,3,0) -> Private | AE100: =IF(Q100="","",Q100*0.05) -> 3285 | AF100: =IF(Q100="","",Q100+AE100) -> 68985 | AG100: =IF(U100="","Not Available",IF(U100>=4,"High",IF(U100=3,"Medium","Low"))) -> High
...

Sheet Patients
A1: Patient ID | B1: Patient Name | C1: Age | D1: Gender | E1: Area | F1: Zone | G1: Blood Type | H1: Chronic Condition | I1: Smoking Status | J1: Risk Group | K1: Registration Date | L1: Emergency Contact Available
A2: P2001 | B2: Mithila Barua | C2: 28 | D2: Female | E2: Savar | F2: Outer Dhaka | G2: AB+ | H2: None | I2: Never | J2: Low | K2: 44488 | L2: Yes
A3: P2002 | B3: Lubna Chowdhury | C3: 80 | D3: Female | E3: Farmgate | F3: Central Dhaka | G3: AB+ | H3: None | I3: Current Smoker | J3: High | K3: 44131 | L3: No
A4: P2003 | B4: Lubna Karim | C4: 73 | D4: Male | E4: Keraniganj | F4: Outer Dhaka | G4: AB+ | H4: Diabetes | I4: Former Smoker | J4: High | K4: 44482 | L4: Yes
A5: P2004 | B5: Mehedi Hasan | C5: 47 | D5: Female | E5: Savar | F5: Outer Dhaka | G5: B- | H5: None | I5: Never | J5: Low | K5: 45351 | L5: Yes
A6: P2005 | B6: Mahmud Barua | C6: 55 | D6: Male | E6: Savar | F6: Outer Dhaka | G6: O- | H6: None | I6: Former Smoker | J6: Medium | K6: 44904 | L6: Yes
A7: P2006 | B7: Sabrina Ahmed | C7: 44 | D7: Female | E7: Uttara | F7: North Dhaka | G7: A- | H7: Asthma | I7: Never | J7: Medium | K7: 45844 | L7: No
A8: P2007 | B8: Farhan Sultana | C8: 28 | D8: Female | E8: Badda | F8: East Dhaka | G8: A+ | H8: Diabetes | I8: Never | J8: Low | K8: 45043 | L8: Yes
A9: P2008 | B9: Tanvir Khan | C9: 33 | D9: Female | E9: Mirpur | F9: North Dhaka | G9: O- | H9: None | I9: Former Smoker | J9: Low | K9: 44273 | L9: Yes
A10: P2009 | B10: Ayesha Islam | C10: 37 | D10: Female | E10: Motijheel | F10: South Dhaka | G10: B- | H10: None | I10: Never | J10: Low | K10: 45114 | L10: Yes
A11: P2010 | B11: Mahmud Barua | C11: 34 | D11: Male | E11: Badda | F11: East Dhaka | G11: A+ | H11: Diabetes | I11: Current Smoker | J11: Medium | K11: 45987 | L11: Yes
A12: P2011 | B12: Hasan Uddin | C12: 38 | D12: Female | E12: Jatrabari | F12: South Dhaka | G12: B+ | H12: Diabetes | I12: Never | J12: Medium | K12: 45277 | L12: Yes
A13: P2012 | B13: Asif Hasan | C13: 55 | D13: Female | E13: Gulshan | F13: North Dhaka | G13: O+ | H13: None | I13: Never | J13: Low | K13: 44838 | L13: Yes
... A601: P2600 | B601: Tareq Jahan | C601: 43 | D601: Female | E601: Wari | F601: South Dhaka | G601: B- | H601: None | I601: Never | J601: Low | K601: 44858 | L601: Yes

Sheet Doctors
A1: Doctor ID | B1: Doctor Name | C1: Department ID | D1: Specialization | E1: Experience Years | F1: Employment Type | G1: Consultation Fee | H1: Weekly Patient Capacity
A2: DR101 | B2: Dr. Imran Karim | C2: D01 | D2: Emergency Medicine | E2: 10 | F2: Full-Time | G2: 1000 | H2: 58
A3: DR102 | B3: Dr. Samira Barua | C3: D01 | D3: Emergency Medicine | E3: 20 | F3: Full-Time | G3: 800 | H3: 56
A4: DR103 | B4: Dr. Farhan Hasan | C4: D01 | D4: Critical Response | E4: 21 | F4: Full-Time | G4: 1000 | H4: 114
A5: DR104 | B5: Dr. Jannat Hasan | C5: D01 | D5: Trauma Care | E5: 20 | F5: Full-Time | G5: 2500 | H5: 45
A6: DR105 | B6: Dr. Asif Chowdhury | C6: D01 | D6: Critical Response | E6: 15 | F6: Full-Time | G6: 1000 | H6: 72
A7: DR106 | B7: Dr. Asif Khan | C7: D01 | D7: Emergency Medicine | E7: 4 | F7: Full-Time | G7: 1200 | H7: 89
A8: DR107 | B8: Dr. Priya Sultana | C8: D02 | D8: Cardiology | E8: 16 | F8: Full-Time | G8: 1500 | H8: 55
A9: DR108 | B9: Dr. Ayesha Jahan | C9: D02 | D9: Heart Failure | E9: 21 | F9: Part-Time | G9: 1200 | H9: 118
A10: DR109 | B10: Dr. Farhan Hossain | C10: D02 | D10: Cardiology | E10: 23 | F10: Full-Time | G10: 1200 | H10: 55
A11: DR110 | B11: Dr. Faria Hasan | C11: D02 | D11: Cardiology | E11: 14 | F11: Full-Time | G11: 2000 | H11: 91
A12: DR111 | B12: Dr. Rakib Das | C12: D02 | D12: Cardiac Imaging | E12: 8 | F12: Full-Time | G12: 2000 | H12: 54
A13: DR112 | B13: Dr. Priya Chowdhury | C13: D02 | D13: Heart Failure | E13: 9 | F13: Full-Time | G13: 1500 | H13: 79
... A61: DR160 | B61: Dr. Mehedi Das | C61: D10 | D61: Gynecology | E61: 19 | F61: Full-Time | G61: 1000 | H61: 50

Sheet Departments
A1: Department ID | B1: Department Name | C1: Floor | D1: Department Head | E1: Monthly Budget | F1: Target Satisfaction Score | G1: Target Readmission Rate | H1: Target Average Stay Days
A2: D01 | B2: Emergency | C2: 1 | D2: Dr. Ayesha Karim | E2: 2500000 | F2: 4.1 | G2: 0.12 | H2: 2
A3: D02 | B3: Cardiology | C3: 5 | D3: Dr. Farhan Ahmed | E3: 3200000 | F3: 4.3 | G3: 0.1 | H3: 4
A4: D03 | B4: Neurology | C4: 6 | D4: Dr. Nadia Rahman | E4: 2800000 | F4: 4.2 | G4: 0.11 | H4: 5
A5: D04 | B5: Orthopedics | C5: 4 | D5: Dr. Saiful Islam | E5: 2100000 | F5: 4 | G5: 0.09 | H5: 3.5
A6: D05 | B6: General Medicine | C6: 3 | D6: Dr. Nusrat Jahan | E6: 1800000 | F6: 4.2 | G6: 0.08 | H6: 2.5
A7: D06 | B7: Surgery | C7: 7 | D7: Dr. Mahmud Hasan | E7: 3600000 | F7: 4.1 | G7: 0.13 | H7: 6
A8: D07 | B8: Pediatrics | C8: 2 | D8: Dr. Sabrina Chowdhury | E8: 1700000 | F8: 4.4 | G8: 0.07 | H8: 2
A9: D08 | B9: Nephrology | C9: 6 | D9: Dr. Tanvir Rahman | E9: 2600000 | F9: 4.1 | G9: 0.14 | H9: 5
A10: D09 | B10: Pulmonology | C10: 5 | D10: Dr. Sharmin Akter | E10: 2300000 | F10: 4 | G10: 0.12 | H10: 4
A11: D10 | B11: Obstetrics | C11: 4 | D11: Dr. Maliha Sultana | E11: 2400000 | F11: 4.3 | G11: 0.06 | H11: 3

Sheet Diagnosis_Guide
A1: Diagnosis Code | B1: Diagnosis Name | C1: Disease Category | D1: Severity Level | E1: Standard Treatment Cost | F1: Expected Stay Days | G1: Criticality Score | H1: Default Department ID
A2: DG01 | B2: Chest Pain | C2: Cardiovascular | D2: Medium | E2: 18000 | F2: 2 | G2: 6 | H2: D02
A3: DG02 | B3: Heart Failure | C3: Cardiovascular | D3: High | E3: 42000 | F3: 5 | G3: 9 | H3: D02
A4: DG03 | B4: Hypertension Crisis | C4: Cardiovascular | D4: High | E4: 30000 | F4: 3 | G4: 8 | H4: D02
A5: DG04 | B5: Stroke Assessment | C5: Neurological | D5: High | E5: 52000 | F5: 6 | G5: 10 | H5: D03
A6: DG05 | B6: Migraine Complication | C6: Neurological | D6: Medium | E6: 16000 | F6: 1 | G6: 5 | H6: D03
A7: DG06 | B7: Seizure Episode | C7: Neurological | D7: High | E7: 31000 | F7: 3 | G7: 8 | H7: D03
A8: DG07 | B8: Fracture Repair | C8: Musculoskeletal | D8: Medium | E8: 35000 | F8: 4 | G8: 7 | H8: D04
A9: DG08 | B9: Joint Pain | C9: Musculoskeletal | D9: Low | E9: 8500 | F9: 1 | G9: 3 | H9: D04
A10: DG09 | B10: Spinal Injury | C10: Musculoskeletal | D10: High | E10: 65000 | F10: 7 | G10: 10 | H10: D04
A11: DG10 | B11: Fever Investigation | C11: Infectious/General | D11: Low | E11: 7000 | F11: 1 | G11: 3 | H11: D05
A12: DG11 | B12: Diabetes Complication | C12: Endocrine/General | D12: Medium | E12: 22000 | F12: 3 | G12: 7 | H12: D05
A13: DG12 | B13: Severe Infection | C13: Infectious/General | D13: High | E13: 45000 | F13: 5 | G13: 9 | H13: D05
... A31: DG30 | B31: Food Poisoning | C31: Emergency | D31: Low | E31: 8000 | F31: 1 | G31: 4 | H31: D01

Sheet Insurance_Plans
A1: Insurance Plan ID | B1: Insurance Provider | C1: Insurance Type | D1: Coverage Percent | E1: Claim Processing Days | F1: Co Pay Amount
A2: IP01 | B2: National Health Support | C2: Public | D2: 0.55 | E2: 12 | F2: 300
A3: IP02 | B3: CarePlus Basic | C3: Private | D3: 0.65 | E3: 8 | F3: 700
A4: IP03 | B4: CarePlus Premium | C4: Private | D4: 0.85 | E4: 5 | F4: 1200
A5: IP04 | B5: Corporate Shield | C5: Employer | D5: 0.75 | E5: 7 | F5: 900
A6: IP05 | B6: Self Pay | C6: Self-Pay | D6: 0 | E6: 0 | F6: 0
A7: IP06 | B7: Senior Care Fund | C7: Public | D7: 0.7 | E7: 10 | F7: 400
A8: IP07 | B8: Micro Health Protect | C8: Community | D8: 0.45 | E8: 15 | F8: 200

Sheet Suggested_KPIs
A1: KPI / Derived Field | B1: Formula Idea | C1: Used For
A2: Actual Length of Stay | B2: Discharge Date - Admission Date | C2: Department efficiency and delay analysis
A3: Stay Variance | B3: Actual Length of Stay - Expected Stay Days | C3: Identify diagnoses causing longer stays
A4: Cost Variance | B4: Total Bill - Standard Treatment Cost | C4: Cost overrun analysis
A5: Cost Variance % | B5: Cost Variance / Standard Treatment Cost | C5: Compare cost overruns fairly
A6: No-Show Flag | B6: Appointment Status is No Show / No-show / Missed | C6: Appointment reliability analysis
A7: Follow-Up Compliance | B7: Follow Up Required = Yes and Follow Up Completed = Yes | C7: Post-discharge care quality
A8: Readmission Rate | B8: Readmitted Within 30 Days = Yes / attended visits | C8: Healthcare outcome quality
A9: Patient Risk Segment | B9: Use Risk Group + Chronic Condition + Age | C9: High-risk patient analysis
